<ArrayOfVETNET_TABLE xmlns:xsi="http://www.w3.org/2001/XMLSchema-instance" xmlns:xsd="http://www.w3.org/2001/XMLSchema"><VETNET_TABLE><ADI/><YAS>4</YAS><DOGUM_TARIHI xsi:type="xsd:dateTime">2014-09-20T00:00:00</DOGUM_TARIHI><SAGLIK_KARNESI>false</SAGLIK_KARNESI><KISIR>true</KISIR><DAVRANIS/><KUPE>false</KUPE><M_UYGULAMA_TARIHI xsi:type="xsd:string"/><TUR_ADI>Köpek</TUR_ADI><IRK_ADI>Melez</IRK_ADI><HAYVAN_MIZAC_ADI/><ANA_RENK>Beyaz</ANA_RENK><TALI_RENK_1>Boz</TALI_RENK_1><TALI_RENK_2/><ISARETLEME_ADI/><GELIS_SEKLI_ADI/><CINSIYET_ADI>Disi</CINSIYET_ADI><ISLEM_TARIHI>2019-12-31T13:46:28</ISLEM_TARIHI></VETNET_TABLE><VETNET_TABLE><ADI>900108001562057</ADI><YAS>5</YAS><DOGUM_TARIHI xsi:type="xsd:dateTime">2013-03-01T00:00:00</DOGUM_TARIHI><SAGLIK_KARNESI>false</SAGLIK_KARNESI><KISIR>true</KISIR><DAVRANIS/><KUPE>false</KUPE><M_UYGULAMA_TARIHI xsi:type="xsd:string"/><TUR_ADI>Köpek</TUR_ADI><IRK_ADI>Melez</IRK_ADI><HAYVAN_MIZAC_ADI/><ANA_RENK>Siyah</ANA_RENK><TALI_RENK_1>Kahverengi</TALI_RENK_1><TALI_RENK_2/><ISARETLEME_ADI/><GELIS_SEKLI_ADI/><CINSIYET_ADI>Disi</CINSIYET_ADI><ISLEM_TARIHI>2019-12-02T14:36:26</ISLEM_TARIHI></VETNET_TABLE><VETNET_TABLE><ADI/><YAS>4</YAS><DOGUM_TARIHI xsi:type="xsd:dateTime">2014-10-24T00:00:00</DOGUM_TARIHI><SAGLIK_KARNESI>false</SAGLIK_KARNESI><KISIR>true</KISIR><DAVRANIS/><KUPE>false</KUPE><M_UYGULAMA_TARIHI xsi:type="xsd:string"/><TUR_ADI>Köpek</TUR_ADI><IRK_ADI>Melez</IRK_ADI><HAYVAN_MIZAC_ADI/><ANA_RENK>Sarı</ANA_RENK><TALI_RENK_1>Boz</TALI_RENK_1><TALI_RENK_2/><ISARETLEME_ADI/><GELIS_SEKLI_ADI/><CINSIYET_ADI>Disi</CINSIYET_ADI><ISLEM_TARIHI>2019-12-09T14:52:46</ISLEM_TARIHI></VETNET_TABLE><VETNET_TABLE><ADI/><YAS>5</YAS><DOGUM_TARIHI xsi:type="xsd:dateTime">2013-02-01T00:00:00</DOGUM_TARIHI><SAGLIK_KARNESI>false</SAGLIK_KARNESI><KISIR>true</KISIR><DAVRANIS>UYSAL</DAVRANIS><KUPE>false</KUPE><M_UYGULAMA_TARIHI xsi:type="xsd:string"/><TUR_ADI>Köpek</TUR_ADI><IRK_ADI>Melez</IRK_ADI><HAYVAN_MIZAC_ADI/><ANA_RENK>Sarı</ANA_RENK><TALI_RENK_1>Beyaz</TALI_RENK_1><TALI_RENK_2/><ISARETLEME_ADI/><GELIS_SEKLI_ADI/><CINSIYET_ADI>Erkek</CINSIYET_ADI><ISLEM_TARIHI>2020-01-07T10:24:12</ISLEM_TARIHI></VETNET_TABLE><VETNET_TABLE><ADI/><YAS>9</YAS><DOGUM_TARIHI xsi:type="xsd:dateTime">2009-01-01T00:00:00</DOGUM_TARIHI><SAGLIK_KARNESI>false</SAGLIK_KARNESI><KISIR>false</KISIR><DAVRANIS>sakin</DAVRANIS><KUPE>false</KUPE><M_UYGULAMA_TARIHI xsi:type="xsd:string"/><TUR_ADI>Köpek</TUR_ADI><IRK_ADI>Melez</IRK_ADI><HAYVAN_MIZAC_ADI/><ANA_RENK>Boz</ANA_RENK><TALI_RENK_1>Boz</TALI_RENK_1><TALI_RENK_2/><ISARETLEME_ADI/><GELIS_SEKLI_ADI/><CINSIYET_ADI>Erkek</CINSIYET_ADI><ISLEM_TARIHI>2019-12-17T13:54:34</ISLEM_TARIHI></VETNET_TABLE><VETNET_TABLE><ADI/><YAS>9</YAS><DOGUM_TARIHI xsi:type="xsd:dateTime">2009-01-01T00:00:00</DOGUM_TARIHI><SAGLIK_KARNESI>false</SAGLIK_KARNESI><KISIR>false</KISIR><DAVRANIS>sakin</DAVRANIS><KUPE>false</KUPE><M_UYGULAMA_TARIHI xsi:type="xsd:string"/><TUR_ADI>Köpek</TUR_ADI><IRK_ADI>Melez</IRK_ADI><HAYVAN_MIZAC_ADI/><ANA_RENK>Kahverengi</ANA_RENK><TALI_RENK_1>Siyah</TALI_RENK_1><TALI_RENK_2/><ISARETLEME_ADI/><GELIS_SEKLI_ADI/><CINSIYET_ADI>Erkek</CINSIYET_ADI><ISLEM_TARIHI>2020-01-15T13:47:32</ISLEM_TARIHI></VETNET_TABLE><VETNET_TABLE><ADI/><YAS>3</YAS><DOGUM_TARIHI xsi:type="xsd:dateTime">2015-05-05T00:00:00</DOGUM_TARIHI><SAGLIK_KARNESI>false</SAGLIK_KARNESI><KISIR>true</KISIR><DAVRANIS/><KUPE>false</KUPE><M_UYGULAMA_TARIHI xsi:type="xsd:string"/><TUR_ADI>Köpek</TUR_ADI><IRK_ADI>Golden Retriever</IRK_ADI><HAYVAN_MIZAC_ADI/><ANA_RENK>Beyaz</ANA_RENK><TALI_RENK_1>Boz</TALI_RENK_1><TALI_RENK_2/><ISARETLEME_ADI/><GELIS_SEKLI_ADI/><CINSIYET_ADI>Erkek</CINSIYET_ADI><ISLEM_TARIHI>2019-12-08T11:47:13</ISLEM_TARIHI></VETNET_TABLE><VETNET_TABLE><ADI/><YAS>3</YAS><DOGUM_TARIHI xsi:type="xsd:dateTime">2015-05-05T00:00:00</DOGUM_TARIHI><SAGLIK_KARNESI>false</SAGLIK_KARNESI><KISIR>true</KISIR><DAVRANIS/><KUPE>false</KUPE><M_UYGULAMA_TARIHI xsi:type="xsd:string"/><TUR_ADI>Köpek</TUR_ADI><IRK_ADI>Melez</IRK_ADI><HAYVAN_MIZAC_ADI/><ANA_RENK>Sarı</ANA_RENK><TALI_RENK_1>Beyaz</TALI_RENK_1><TALI_RENK_2/><ISARETLEME_ADI/><GELIS_SEKLI_ADI/><CINSIYET_ADI>Disi</CINSIYET_ADI><ISLEM_TARIHI>2020-01-15T13:47:29</ISLEM_TARIHI></VETNET_TABLE><VETNET_TABLE><ADI/><YAS>2</YAS><DOGUM_TARIHI xsi:type="xsd:dateTime">2016-09-30T00:00:00</DOGUM_TARIHI><SAGLIK_KARNESI>false</SAGLIK_KARNESI><KISIR>false</KISIR><DAVRANIS/><KUPE>false</KUPE><M_UYGULAMA_TARIHI xsi:type="xsd:string"/><TUR_ADI>Köpek</TUR_ADI><IRK_ADI>Melez</IRK_ADI><HAYVAN_MIZAC_ADI/><ANA_RENK>Sarı</ANA_RENK><TALI_RENK_1>Sarı</TALI_RENK_1><TALI_RENK_2/><ISARETLEME_ADI>YOK</ISARETLEME_ADI><GELIS_SEKLI_ADI/><CINSIYET_ADI>Erkek</CINSIYET_ADI><ISLEM_TARIHI>2019-12-04T15:49:41</ISLEM_TARIHI></VETNET_TABLE><VETNET_TABLE><ADI/><YAS>4</YAS><DOGUM_TARIHI xsi:type="xsd:string"/><SAGLIK_KARNESI>false</SAGLIK_KARNESI><KISIR>false</KISIR><DAVRANIS/><KUPE>false</KUPE><M_UYGULAMA_TARIHI xsi:type="xsd:string"/><TUR_ADI>Köpek</TUR_ADI><IRK_ADI>Golden Retriever</IRK_ADI><HAYVAN_MIZAC_ADI/><ANA_RENK>Sarı</ANA_RENK><TALI_RENK_1>Sarı</TALI_RENK_1><TALI_RENK_2/><ISARETLEME_ADI>YOK</ISARETLEME_ADI><GELIS_SEKLI_ADI/><CINSIYET_ADI>Disi</CINSIYET_ADI><ISLEM_TARIHI>2019-12-16T13:38:35</ISLEM_TARIHI></VETNET_TABLE><VETNET_TABLE><ADI/><YAS>1</YAS><DOGUM_TARIHI xsi:type="xsd:dateTime">2017-01-01T00:00:00</DOGUM_TARIHI><SAGLIK_KARNESI>false</SAGLIK_KARNESI><KISIR>true</KISIR><DAVRANIS>UYSAL</DAVRANIS><KUPE>false</KUPE><M_UYGULAMA_TARIHI xsi:type="xsd:string"/><TUR_ADI>Köpek</TUR_ADI><IRK_ADI>Melez</IRK_ADI><HAYVAN_MIZAC_ADI/><ANA_RENK>Beyaz</ANA_RENK><TALI_RENK_1>Boz</TALI_RENK_1><TALI_RENK_2/><ISARETLEME_ADI/><GELIS_SEKLI_ADI/><CINSIYET_ADI>Disi</CINSIYET_ADI><ISLEM_TARIHI>2019-12-12T15:29:24</ISLEM_TARIHI></VETNET_TABLE><VETNET_TABLE><ADI/><YAS>1</YAS><DOGUM_TARIHI xsi:type="xsd:dateTime">2016-01-01T00:00:00</DOGUM_TARIHI><SAGLIK_KARNESI>false</SAGLIK_KARNESI><KISIR>true</KISIR><DAVRANIS>uysal</DAVRANIS><KUPE>false</KUPE><M_UYGULAMA_TARIHI xsi:type="xsd:string"/><TUR_ADI>Köpek</TUR_ADI><IRK_ADI>Melez</IRK_ADI><HAYVAN_MIZAC_ADI/><ANA_RENK>Kahverengi</ANA_RENK><TALI_RENK_1>Beyaz</TALI_RENK_1><TALI_RENK_2/><ISARETLEME_ADI/><GELIS_SEKLI_ADI/><CINSIYET_ADI>Erkek</CINSIYET_ADI><ISLEM_TARIHI>2019-12-13T16:07:09</ISLEM_TARIHI></VETNET_TABLE><VETNET_TABLE><ADI/><YAS>2</YAS><DOGUM_TARIHI xsi:type="xsd:string"/><SAGLIK_KARNESI>false</SAGLIK_KARNESI><KISIR>false</KISIR><DAVRANIS/><KUPE>false</KUPE><M_UYGULAMA_TARIHI xsi:type="xsd:dateTime">2018-12-11T00:00:00</M_UYGULAMA_TARIHI><TUR_ADI>Kedi</TUR_ADI><IRK_ADI>Melez</IRK_ADI><HAYVAN_MIZAC_ADI/><ANA_RENK>Tekir</ANA_RENK><TALI_RENK_1>Beyaz</TALI_RENK_1><TALI_RENK_2/><ISARETLEME_ADI>YOK</ISARETLEME_ADI><GELIS_SEKLI_ADI/><CINSIYET_ADI>Disi</CINSIYET_ADI><ISLEM_TARIHI>2020-01-03T11:25:55</ISLEM_TARIHI></VETNET_TABLE><VETNET_TABLE><ADI/><YAS>2</YAS><DOGUM_TARIHI xsi:type="xsd:string"/><SAGLIK_KARNESI>false</SAGLIK_KARNESI><KISIR>true</KISIR><DAVRANIS/><KUPE>false</KUPE><M_UYGULAMA_TARIHI xsi:type="xsd:dateTime">2019-02-20T00:00:00</M_UYGULAMA_TARIHI><TUR_ADI>Köpek</TUR_ADI><IRK_ADI>Melez</IRK_ADI><HAYVAN_MIZAC_ADI/><ANA_RENK>Siyah</ANA_RENK><TALI_RENK_1>Beyaz</TALI_RENK_1><TALI_RENK_2/><ISARETLEME_ADI>TATOO</ISARETLEME_ADI><GELIS_SEKLI_ADI/><CINSIYET_ADI>Erkek</CINSIYET_ADI><ISLEM_TARIHI>2019-12-03T14:35:22</ISLEM_TARIHI></VETNET_TABLE><VETNET_TABLE><ADI/><YAS>8</YAS><DOGUM_TARIHI xsi:type="xsd:string"/><SAGLIK_KARNESI>false</SAGLIK_KARNESI><KISIR>true</KISIR><DAVRANIS/><KUPE>false</KUPE><M_UYGULAMA_TARIHI xsi:type="xsd:dateTime">2019-05-23T00:00:00</M_UYGULAMA_TARIHI><TUR_ADI>Köpek</TUR_ADI><IRK_ADI>Melez</IRK_ADI><HAYVAN_MIZAC_ADI/><ANA_RENK>Siyah</ANA_RENK><TALI_RENK_1>Beyaz</TALI_RENK_1><TALI_RENK_2>Kahverengi</TALI_RENK_2><ISARETLEME_ADI>YOK</ISARETLEME_ADI><GELIS_SEKLI_ADI>Yakalanarak</GELIS_SEKLI_ADI><CINSIYET_ADI>Erkek</CINSIYET_ADI><ISLEM_TARIHI>2019-12-18T14:34:25</ISLEM_TARIHI></VETNET_TABLE><VETNET_TABLE><ADI/><YAS>1</YAS><DOGUM_TARIHI xsi:type="xsd:string"/><SAGLIK_KARNESI>false</SAGLIK_KARNESI><KISIR>true</KISIR><DAVRANIS/><KUPE>false</KUPE><M_UYGULAMA_TARIHI xsi:type="xsd:dateTime">2019-06-10T00:00:00</M_UYGULAMA_TARIHI><TUR_ADI>Köpek</TUR_ADI><IRK_ADI>Melez</IRK_ADI><HAYVAN_MIZAC_ADI/><ANA_RENK>Boz</ANA_RENK><TALI_RENK_1>Boz</TALI_RENK_1><TALI_RENK_2/><ISARETLEME_ADI>TATOO</ISARETLEME_ADI><GELIS_SEKLI_ADI/><CINSIYET_ADI>Disi</CINSIYET_ADI><ISLEM_TARIHI>2019-12-04T15:49:52</ISLEM_TARIHI></VETNET_TABLE><VETNET_TABLE><ADI/><YAS>2</YAS><DOGUM_TARIHI xsi:type="xsd:string"/><SAGLIK_KARNESI>false</SAGLIK_KARNESI><KISIR>true</KISIR><DAVRANIS/><KUPE>false</KUPE><M_UYGULAMA_TARIHI xsi:type="xsd:dateTime">2019-06-18T00:00:00</M_UYGULAMA_TARIHI><TUR_ADI>Köpek</TUR_ADI><IRK_ADI>Melez</IRK_ADI><HAYVAN_MIZAC_ADI/><ANA_RENK>Kahverengi</ANA_RENK><TALI_RENK_1>Siyah</TALI_RENK_1><TALI_RENK_2/><ISARETLEME_ADI>TATOO</ISARETLEME_ADI><GELIS_SEKLI_ADI/><CINSIYET_ADI>Disi</CINSIYET_ADI><ISLEM_TARIHI>2019-12-04T15:49:59</ISLEM_TARIHI></VETNET_TABLE><VETNET_TABLE><ADI/><YAS>6</YAS><DOGUM_TARIHI xsi:type="xsd:string"/><SAGLIK_KARNESI>false</SAGLIK_KARNESI><KISIR>false</KISIR><DAVRANIS/><KUPE>false</KUPE><M_UYGULAMA_TARIHI xsi:type="xsd:dateTime">2019-06-27T00:00:00</M_UYGULAMA_TARIHI><TUR_ADI>At</TUR_ADI><IRK_ADI>Anadolu Atı</IRK_ADI><HAYVAN_MIZAC_ADI/><ANA_RENK>Beyaz</ANA_RENK><TALI_RENK_1>Beyaz</TALI_RENK_1><TALI_RENK_2/><ISARETLEME_ADI>YOK</ISARETLEME_ADI><GELIS_SEKLI_ADI/><CINSIYET_ADI>Disi</CINSIYET_ADI><ISLEM_TARIHI>2020-01-06T12:04:25</ISLEM_TARIHI></VETNET_TABLE><VETNET_TABLE><ADI/><YAS>2</YAS><DOGUM_TARIHI xsi:type="xsd:dateTime">2017-01-01T00:00:00</DOGUM_TARIHI><SAGLIK_KARNESI>false</SAGLIK_KARNESI><KISIR>true</KISIR><DAVRANIS>Uysal</DAVRANIS><KUPE>false</KUPE><M_UYGULAMA_TARIHI xsi:type="xsd:dateTime">2019-08-27T00:00:00</M_UYGULAMA_TARIHI><TUR_ADI>Köpek</TUR_ADI><IRK_ADI>Melez</IRK_ADI><HAYVAN_MIZAC_ADI/><ANA_RENK>Sarı</ANA_RENK><TALI_RENK_1>Sarı</TALI_RENK_1><TALI_RENK_2/><ISARETLEME_ADI>YOK</ISARETLEME_ADI><GELIS_SEKLI_ADI>Bayıltarak</GELIS_SEKLI_ADI><CINSIYET_ADI>Erkek</CINSIYET_ADI><ISLEM_TARIHI>2019-12-12T15:39:12</ISLEM_TARIHI></VETNET_TABLE><VETNET_TABLE><ADI/><YAS>3</YAS><DOGUM_TARIHI xsi:type="xsd:dateTime">2016-10-01T00:00:00</DOGUM_TARIHI><SAGLIK_KARNESI>false</SAGLIK_KARNESI><KISIR>true</KISIR><DAVRANIS/><KUPE>false</KUPE><M_UYGULAMA_TARIHI xsi:type="xsd:dateTime">2019-10-07T00:00:00</M_UYGULAMA_TARIHI><TUR_ADI>Köpek</TUR_ADI><IRK_ADI>Fransız buldog</IRK_ADI><HAYVAN_MIZAC_ADI/><ANA_RENK>Krem</ANA_RENK><TALI_RENK_1>Krem</TALI_RENK_1><TALI_RENK_2/><ISARETLEME_ADI>YOK</ISARETLEME_ADI><GELIS_SEKLI_ADI>Teslim</GELIS_SEKLI_ADI><CINSIYET_ADI>Erkek</CINSIYET_ADI><ISLEM_TARIHI>2020-01-20T13:27:06</ISLEM_TARIHI></VETNET_TABLE><VETNET_TABLE><ADI/><YAS>5</YAS><DOGUM_TARIHI xsi:type="xsd:dateTime">2015-01-01T00:00:00</DOGUM_TARIHI><SAGLIK_KARNESI>false</SAGLIK_KARNESI><KISIR>false</KISIR><DAVRANIS/><KUPE>false</KUPE><M_UYGULAMA_TARIHI xsi:type="xsd:dateTime">2019-10-15T00:00:00</M_UYGULAMA_TARIHI><TUR_ADI>Köpek</TUR_ADI><IRK_ADI>Kangal Çoban</IRK_ADI><HAYVAN_MIZAC_ADI/><ANA_RENK>Kahverengi</ANA_RENK><TALI_RENK_1>Kahverengi</TALI_RENK_1><TALI_RENK_2/><ISARETLEME_ADI>YOK</ISARETLEME_ADI><GELIS_SEKLI_ADI>Teslim</GELIS_SEKLI_ADI><CINSIYET_ADI>Erkek</CINSIYET_ADI><ISLEM_TARIHI>2020-01-20T13:27:03</ISLEM_TARIHI></VETNET_TABLE><VETNET_TABLE><ADI/><YAS>1</YAS><DOGUM_TARIHI xsi:type="xsd:dateTime">2019-05-05T00:00:00</DOGUM_TARIHI><SAGLIK_KARNESI>false</SAGLIK_KARNESI><KISIR>false</KISIR><DAVRANIS/><KUPE>false</KUPE><M_UYGULAMA_TARIHI xsi:type="xsd:dateTime">2019-10-15T00:00:00</M_UYGULAMA_TARIHI><TUR_ADI>Köpek</TUR_ADI><IRK_ADI>Melez</IRK_ADI><HAYVAN_MIZAC_ADI/><ANA_RENK>Krem</ANA_RENK><TALI_RENK_1>Siyah</TALI_RENK_1><TALI_RENK_2/><ISARETLEME_ADI>YOK</ISARETLEME_ADI><GELIS_SEKLI_ADI>Yakalanarak</GELIS_SEKLI_ADI><CINSIYET_ADI>Disi</CINSIYET_ADI><ISLEM_TARIHI>2020-01-20T13:45:41</ISLEM_TARIHI></VETNET_TABLE><VETNET_TABLE><ADI/><YAS>1</YAS><DOGUM_TARIHI xsi:type="xsd:string"/><SAGLIK_KARNESI>false</SAGLIK_KARNESI><KISIR>true</KISIR><DAVRANIS/><KUPE>false</KUPE><M_UYGULAMA_TARIHI xsi:type="xsd:dateTime">2019-10-31T00:00:00</M_UYGULAMA_TARIHI><TUR_ADI>Köpek</TUR_ADI><IRK_ADI>Terrier</IRK_ADI><HAYVAN_MIZAC_ADI/><ANA_RENK>Beyaz</ANA_RENK><TALI_RENK_1>Beyaz</TALI_RENK_1><TALI_RENK_2/><ISARETLEME_ADI>TATOO</ISARETLEME_ADI><GELIS_SEKLI_ADI>Teslim</GELIS_SEKLI_ADI><CINSIYET_ADI>Disi</CINSIYET_ADI><ISLEM_TARIHI>2019-12-22T13:11:51</ISLEM_TARIHI></VETNET_TABLE><VETNET_TABLE><ADI/><YAS>2</YAS><DOGUM_TARIHI xsi:type="xsd:string"/><SAGLIK_KARNESI>false</SAGLIK_KARNESI><KISIR>true</KISIR><DAVRANIS/><KUPE>false</KUPE><M_UYGULAMA_TARIHI xsi:type="xsd:dateTime">2019-10-31T00:00:00</M_UYGULAMA_TARIHI><TUR_ADI>Köpek</TUR_ADI><IRK_ADI>Labrador Retriever</IRK_ADI><HAYVAN_MIZAC_ADI/><ANA_RENK>Siyah</ANA_RENK><TALI_RENK_1>Beyaz</TALI_RENK_1><TALI_RENK_2/><ISARETLEME_ADI>TATOO</ISARETLEME_ADI><GELIS_SEKLI_ADI/><CINSIYET_ADI>Erkek</CINSIYET_ADI><ISLEM_TARIHI>2020-01-09T10:53:07</ISLEM_TARIHI></VETNET_TABLE><VETNET_TABLE><ADI/><YAS>2</YAS><DOGUM_TARIHI xsi:type="xsd:string"/><SAGLIK_KARNESI>false</SAGLIK_KARNESI><KISIR>true</KISIR><DAVRANIS/><KUPE>false</KUPE><M_UYGULAMA_TARIHI xsi:type="xsd:dateTime">2019-11-04T00:00:00</M_UYGULAMA_TARIHI><TUR_ADI>Köpek</TUR_ADI><IRK_ADI>Melez</IRK_ADI><HAYVAN_MIZAC_ADI/><ANA_RENK>Siyah</ANA_RENK><TALI_RENK_1>Kahverengi</TALI_RENK_1><TALI_RENK_2/><ISARETLEME_ADI>YOK</ISARETLEME_ADI><GELIS_SEKLI_ADI>Yakalanarak</GELIS_SEKLI_ADI><CINSIYET_ADI>Erkek</CINSIYET_ADI><ISLEM_TARIHI>2019-12-02T14:36:59</ISLEM_TARIHI></VETNET_TABLE><VETNET_TABLE><ADI/><YAS>3</YAS><DOGUM_TARIHI xsi:type="xsd:string"/><SAGLIK_KARNESI>false</SAGLIK_KARNESI><KISIR>false</KISIR><DAVRANIS/><KUPE>false</KUPE><M_UYGULAMA_TARIHI xsi:type="xsd:dateTime">2019-11-05T00:00:00</M_UYGULAMA_TARIHI><TUR_ADI>At</TUR_ADI><IRK_ADI>Melez</IRK_ADI><HAYVAN_MIZAC_ADI/><ANA_RENK>Boz</ANA_RENK><TALI_RENK_1>Beyaz</TALI_RENK_1><TALI_RENK_2/><ISARETLEME_ADI>YOK</ISARETLEME_ADI><GELIS_SEKLI_ADI/><CINSIYET_ADI>Disi</CINSIYET_ADI><ISLEM_TARIHI>2020-01-06T12:04:21</ISLEM_TARIHI></VETNET_TABLE><VETNET_TABLE><ADI/><YAS>3</YAS><DOGUM_TARIHI xsi:type="xsd:string"/><SAGLIK_KARNESI>false</SAGLIK_KARNESI><KISIR>false</KISIR><DAVRANIS/><KUPE>false</KUPE><M_UYGULAMA_TARIHI xsi:type="xsd:dateTime">2019-11-10T00:00:00</M_UYGULAMA_TARIHI><TUR_ADI>Kedi</TUR_ADI><IRK_ADI>British Shorthair</IRK_ADI><HAYVAN_MIZAC_ADI/><ANA_RENK>Gri</ANA_RENK><TALI_RENK_1>Gri</TALI_RENK_1><TALI_RENK_2/><ISARETLEME_ADI>YOK</ISARETLEME_ADI><GELIS_SEKLI_ADI/><CINSIYET_ADI>Erkek</CINSIYET_ADI><ISLEM_TARIHI>2019-12-04T13:56:57</ISLEM_TARIHI></VETNET_TABLE><VETNET_TABLE><ADI/><YAS>3</YAS><DOGUM_TARIHI xsi:type="xsd:string"/><SAGLIK_KARNESI>false</SAGLIK_KARNESI><KISIR>true</KISIR><DAVRANIS/><KUPE>false</KUPE><M_UYGULAMA_TARIHI xsi:type="xsd:dateTime">2019-11-11T00:00:00</M_UYGULAMA_TARIHI><TUR_ADI>Köpek</TUR_ADI><IRK_ADI>Golden Retriever</IRK_ADI><HAYVAN_MIZAC_ADI/><ANA_RENK>Kahverengi</ANA_RENK><TALI_RENK_1>Kahverengi</TALI_RENK_1><TALI_RENK_2/><ISARETLEME_ADI>TATOO</ISARETLEME_ADI><GELIS_SEKLI_ADI/><CINSIYET_ADI>Erkek</CINSIYET_ADI><ISLEM_TARIHI>2019-12-04T15:48:40</ISLEM_TARIHI></VETNET_TABLE><VETNET_TABLE><ADI/><YAS>3</YAS><DOGUM_TARIHI xsi:type="xsd:string"/><SAGLIK_KARNESI>false</SAGLIK_KARNESI><KISIR>true</KISIR><DAVRANIS/><KUPE>false</KUPE><M_UYGULAMA_TARIHI xsi:type="xsd:dateTime">2019-11-11T00:00:00</M_UYGULAMA_TARIHI><TUR_ADI>Köpek</TUR_ADI><IRK_ADI>Golden Retriever</IRK_ADI><HAYVAN_MIZAC_ADI/><ANA_RENK>Kahverengi</ANA_RENK><TALI_RENK_1>Kahverengi</TALI_RENK_1><TALI_RENK_2/><ISARETLEME_ADI>TATOO</ISARETLEME_ADI><GELIS_SEKLI_ADI/><CINSIYET_ADI>Erkek</CINSIYET_ADI><ISLEM_TARIHI>2019-12-23T15:29:36</ISLEM_TARIHI></VETNET_TABLE><VETNET_TABLE><ADI/><YAS>2</YAS><DOGUM_TARIHI xsi:type="xsd:dateTime">2017-01-01T00:00:00</DOGUM_TARIHI><SAGLIK_KARNESI>false</SAGLIK_KARNESI><KISIR>true</KISIR><DAVRANIS>Uysal</DAVRANIS><KUPE>false</KUPE><M_UYGULAMA_TARIHI xsi:type="xsd:dateTime">2019-11-11T00:00:00</M_UYGULAMA_TARIHI><TUR_ADI>Köpek</TUR_ADI><IRK_ADI>Melez</IRK_ADI><HAYVAN_MIZAC_ADI/><ANA_RENK>Siyah</ANA_RENK><TALI_RENK_1>Beyaz</TALI_RENK_1><TALI_RENK_2/><ISARETLEME_ADI>YOK</ISARETLEME_ADI><GELIS_SEKLI_ADI>Bayıltarak</GELIS_SEKLI_ADI><CINSIYET_ADI>Disi</CINSIYET_ADI><ISLEM_TARIHI>2019-12-16T16:53:29</ISLEM_TARIHI></VETNET_TABLE><VETNET_TABLE><ADI/><YAS>3</YAS><DOGUM_TARIHI xsi:type="xsd:string"/><SAGLIK_KARNESI>false</SAGLIK_KARNESI><KISIR>false</KISIR><DAVRANIS/><KUPE>false</KUPE><M_UYGULAMA_TARIHI xsi:type="xsd:dateTime">2019-11-12T00:00:00</M_UYGULAMA_TARIHI><TUR_ADI>Kedi</TUR_ADI><IRK_ADI>Melez</IRK_ADI><HAYVAN_MIZAC_ADI/><ANA_RENK>Sarı</ANA_RENK><TALI_RENK_1>Beyaz</TALI_RENK_1><TALI_RENK_2/><ISARETLEME_ADI>YOK</ISARETLEME_ADI><GELIS_SEKLI_ADI/><CINSIYET_ADI>Erkek</CINSIYET_ADI><ISLEM_TARIHI>2019-12-21T09:17:29</ISLEM_TARIHI></VETNET_TABLE><VETNET_TABLE><ADI/><YAS>2</YAS><DOGUM_TARIHI xsi:type="xsd:string"/><SAGLIK_KARNESI>false</SAGLIK_KARNESI><KISIR>false</KISIR><DAVRANIS/><KUPE>false</KUPE><M_UYGULAMA_TARIHI xsi:type="xsd:dateTime">2019-11-13T00:00:00</M_UYGULAMA_TARIHI><TUR_ADI>Kedi</TUR_ADI><IRK_ADI>Melez</IRK_ADI><HAYVAN_MIZAC_ADI/><ANA_RENK>Siyah</ANA_RENK><TALI_RENK_1>Kahverengi</TALI_RENK_1><TALI_RENK_2/><ISARETLEME_ADI>YOK</ISARETLEME_ADI><GELIS_SEKLI_ADI/><CINSIYET_ADI>Disi</CINSIYET_ADI><ISLEM_TARIHI>2019-12-17T13:54:30</ISLEM_TARIHI></VETNET_TABLE><VETNET_TABLE><ADI/><YAS>1</YAS><DOGUM_TARIHI xsi:type="xsd:string"/><SAGLIK_KARNESI>false</SAGLIK_KARNESI><KISIR>true</KISIR><DAVRANIS/><KUPE>false</KUPE><M_UYGULAMA_TARIHI xsi:type="xsd:dateTime">2019-11-20T00:00:00</M_UYGULAMA_TARIHI><TUR_ADI>Köpek</TUR_ADI><IRK_ADI>Akbaş</IRK_ADI><HAYVAN_MIZAC_ADI/><ANA_RENK>Krem</ANA_RENK><TALI_RENK_1>Krem</TALI_RENK_1><TALI_RENK_2/><ISARETLEME_ADI>TATOO</ISARETLEME_ADI><GELIS_SEKLI_ADI/><CINSIYET_ADI>Disi</CINSIYET_ADI><ISLEM_TARIHI>2019-12-02T14:36:49</ISLEM_TARIHI></VETNET_TABLE><VETNET_TABLE><ADI/><YAS>2</YAS><DOGUM_TARIHI xsi:type="xsd:string"/><SAGLIK_KARNESI>false</SAGLIK_KARNESI><KISIR>true</KISIR><DAVRANIS/><KUPE>false</KUPE><M_UYGULAMA_TARIHI xsi:type="xsd:dateTime">2019-11-22T00:00:00</M_UYGULAMA_TARIHI><TUR_ADI>Köpek</TUR_ADI><IRK_ADI>Melez</IRK_ADI><HAYVAN_MIZAC_ADI/><ANA_RENK>Kahverengi</ANA_RENK><TALI_RENK_1>Kahverengi</TALI_RENK_1><TALI_RENK_2/><ISARETLEME_ADI>TATOO</ISARETLEME_ADI><GELIS_SEKLI_ADI/><CINSIYET_ADI>Erkek</CINSIYET_ADI><ISLEM_TARIHI>2019-12-17T13:54:51</ISLEM_TARIHI></VETNET_TABLE><VETNET_TABLE><ADI/><YAS>2</YAS><DOGUM_TARIHI xsi:type="xsd:string"/><SAGLIK_KARNESI>false</SAGLIK_KARNESI><KISIR>true</KISIR><DAVRANIS/><KUPE>false</KUPE><M_UYGULAMA_TARIHI xsi:type="xsd:dateTime">2019-11-22T00:00:00</M_UYGULAMA_TARIHI><TUR_ADI>Kedi</TUR_ADI><IRK_ADI>Melez</IRK_ADI><HAYVAN_MIZAC_ADI/><ANA_RENK>Siyah</ANA_RENK><TALI_RENK_1>Siyah</TALI_RENK_1><TALI_RENK_2/><ISARETLEME_ADI>YOK</ISARETLEME_ADI><GELIS_SEKLI_ADI/><CINSIYET_ADI>Disi</CINSIYET_ADI><ISLEM_TARIHI>2019-12-23T15:29:29</ISLEM_TARIHI></VETNET_TABLE><VETNET_TABLE><ADI/><YAS>3</YAS><DOGUM_TARIHI xsi:type="xsd:string"/><SAGLIK_KARNESI>false</SAGLIK_KARNESI><KISIR>false</KISIR><DAVRANIS/><KUPE>false</KUPE><M_UYGULAMA_TARIHI xsi:type="xsd:dateTime">2019-11-22T00:00:00</M_UYGULAMA_TARIHI><TUR_ADI>Kedi</TUR_ADI><IRK_ADI>Melez</IRK_ADI><HAYVAN_MIZAC_ADI/><ANA_RENK>Siyah</ANA_RENK><TALI_RENK_1>Siyah</TALI_RENK_1><TALI_RENK_2/><ISARETLEME_ADI>YOK</ISARETLEME_ADI><GELIS_SEKLI_ADI/><CINSIYET_ADI>Erkek</CINSIYET_ADI><ISLEM_TARIHI>2019-12-02T14:36:33</ISLEM_TARIHI></VETNET_TABLE><VETNET_TABLE><ADI/><YAS>3</YAS><DOGUM_TARIHI xsi:type="xsd:string"/><SAGLIK_KARNESI>false</SAGLIK_KARNESI><KISIR>false</KISIR><DAVRANIS/><KUPE>false</KUPE><M_UYGULAMA_TARIHI xsi:type="xsd:string"/><TUR_ADI>Kedi</TUR_ADI><IRK_ADI>Melez</IRK_ADI><HAYVAN_MIZAC_ADI/><ANA_RENK>Siyah</ANA_RENK><TALI_RENK_1>Beyaz</TALI_RENK_1><TALI_RENK_2/><ISARETLEME_ADI>YOK</ISARETLEME_ADI><GELIS_SEKLI_ADI/><CINSIYET_ADI>Erkek</CINSIYET_ADI><ISLEM_TARIHI>2019-12-02T14:36:42</ISLEM_TARIHI></VETNET_TABLE><VETNET_TABLE><ADI/><YAS>3</YAS><DOGUM_TARIHI xsi:type="xsd:dateTime">2017-01-01T00:00:00</DOGUM_TARIHI><SAGLIK_KARNESI>false</SAGLIK_KARNESI><KISIR>false</KISIR><DAVRANIS/><KUPE>false</KUPE><M_UYGULAMA_TARIHI xsi:type="xsd:dateTime">2019-11-13T00:00:00</M_UYGULAMA_TARIHI><TUR_ADI>Kedi</TUR_ADI><IRK_ADI>Melez</IRK_ADI><HAYVAN_MIZAC_ADI/><ANA_RENK>Sarı</ANA_RENK><TALI_RENK_1>Beyaz</TALI_RENK_1><TALI_RENK_2/><ISARETLEME_ADI>YOK</ISARETLEME_ADI><GELIS_SEKLI_ADI>Teslim</GELIS_SEKLI_ADI><CINSIYET_ADI>Erkek</CINSIYET_ADI><ISLEM_TARIHI>2019-12-08T11:47:27</ISLEM_TARIHI></VETNET_TABLE><VETNET_TABLE><ADI/><YAS>2</YAS><DOGUM_TARIHI xsi:type="xsd:string"/><SAGLIK_KARNESI>false</SAGLIK_KARNESI><KISIR>false</KISIR><DAVRANIS/><KUPE>false</KUPE><M_UYGULAMA_TARIHI xsi:type="xsd:string"/><TUR_ADI>Köpek</TUR_ADI><IRK_ADI>Melez</IRK_ADI><HAYVAN_MIZAC_ADI/><ANA_RENK>Sarı</ANA_RENK><TALI_RENK_1>Beyaz</TALI_RENK_1><TALI_RENK_2/><ISARETLEME_ADI>YOK</ISARETLEME_ADI><GELIS_SEKLI_ADI/><CINSIYET_ADI>Disi</CINSIYET_ADI><ISLEM_TARIHI>2019-12-10T12:31:14</ISLEM_TARIHI></VETNET_TABLE><VETNET_TABLE><ADI/><YAS>2</YAS><DOGUM_TARIHI xsi:type="xsd:string"/><SAGLIK_KARNESI>false</SAGLIK_KARNESI><KISIR>false</KISIR><DAVRANIS/><KUPE>false</KUPE><M_UYGULAMA_TARIHI xsi:type="xsd:string"/><TUR_ADI>Kedi</TUR_ADI><IRK_ADI>Melez</IRK_ADI><HAYVAN_MIZAC_ADI/><ANA_RENK>Gri</ANA_RENK><TALI_RENK_1>Beyaz</TALI_RENK_1><TALI_RENK_2/><ISARETLEME_ADI>YOK</ISARETLEME_ADI><GELIS_SEKLI_ADI/><CINSIYET_ADI>Disi</CINSIYET_ADI><ISLEM_TARIHI>2019-12-02T14:37:06</ISLEM_TARIHI></VETNET_TABLE><VETNET_TABLE><ADI/><YAS>7</YAS><DOGUM_TARIHI xsi:type="xsd:string"/><SAGLIK_KARNESI>false</SAGLIK_KARNESI><KISIR>false</KISIR><DAVRANIS/><KUPE>false</KUPE><M_UYGULAMA_TARIHI xsi:type="xsd:string"/><TUR_ADI>Köpek</TUR_ADI><IRK_ADI>Melez</IRK_ADI><HAYVAN_MIZAC_ADI/><ANA_RENK>Kahverengi</ANA_RENK><TALI_RENK_1>Kahverengi</TALI_RENK_1><TALI_RENK_2/><ISARETLEME_ADI>YOK</ISARETLEME_ADI><GELIS_SEKLI_ADI/><CINSIYET_ADI>Erkek</CINSIYET_ADI><ISLEM_TARIHI>2019-12-17T13:54:43</ISLEM_TARIHI></VETNET_TABLE><VETNET_TABLE><ADI/><YAS>2</YAS><DOGUM_TARIHI xsi:type="xsd:dateTime">2017-01-01T00:00:00</DOGUM_TARIHI><SAGLIK_KARNESI>false</SAGLIK_KARNESI><KISIR>true</KISIR><DAVRANIS>Uysal</DAVRANIS><KUPE>false</KUPE><M_UYGULAMA_TARIHI xsi:type="xsd:dateTime">2019-11-27T00:00:00</M_UYGULAMA_TARIHI><TUR_ADI>Köpek</TUR_ADI><IRK_ADI>Melez</IRK_ADI><HAYVAN_MIZAC_ADI/><ANA_RENK>Siyah</ANA_RENK><TALI_RENK_1>Kahverengi</TALI_RENK_1><TALI_RENK_2/><ISARETLEME_ADI>YOK</ISARETLEME_ADI><GELIS_SEKLI_ADI>Bayıltarak</GELIS_SEKLI_ADI><CINSIYET_ADI>Disi</CINSIYET_ADI><ISLEM_TARIHI>2019-12-13T16:10:35</ISLEM_TARIHI></VETNET_TABLE><VETNET_TABLE><ADI/><YAS>1</YAS><DOGUM_TARIHI xsi:type="xsd:dateTime">2018-01-01T00:00:00</DOGUM_TARIHI><SAGLIK_KARNESI>false</SAGLIK_KARNESI><KISIR>true</KISIR><DAVRANIS>Uysal</DAVRANIS><KUPE>false</KUPE><M_UYGULAMA_TARIHI xsi:type="xsd:dateTime">2019-11-27T00:00:00</M_UYGULAMA_TARIHI><TUR_ADI>Köpek</TUR_ADI><IRK_ADI>Melez</IRK_ADI><HAYVAN_MIZAC_ADI/><ANA_RENK>Sarı</ANA_RENK><TALI_RENK_1>Sarı</TALI_RENK_1><TALI_RENK_2/><ISARETLEME_ADI>YOK</ISARETLEME_ADI><GELIS_SEKLI_ADI>Bayıltarak</GELIS_SEKLI_ADI><CINSIYET_ADI>Disi</CINSIYET_ADI><ISLEM_TARIHI>2019-12-12T15:49:59</ISLEM_TARIHI></VETNET_TABLE><VETNET_TABLE><ADI/><YAS>4</YAS><DOGUM_TARIHI xsi:type="xsd:string"/><SAGLIK_KARNESI>false</SAGLIK_KARNESI><KISIR>false</KISIR><DAVRANIS/><KUPE>false</KUPE><M_UYGULAMA_TARIHI xsi:type="xsd:string"/><TUR_ADI>Köpek</TUR_ADI><IRK_ADI>Rottweiler</IRK_ADI><HAYVAN_MIZAC_ADI/><ANA_RENK>Siyah</ANA_RENK><TALI_RENK_1>Siyah</TALI_RENK_1><TALI_RENK_2/><ISARETLEME_ADI>YOK</ISARETLEME_ADI><GELIS_SEKLI_ADI/><CINSIYET_ADI>Disi</CINSIYET_ADI><ISLEM_TARIHI>2019-12-10T12:41:27</ISLEM_TARIHI></VETNET_TABLE><VETNET_TABLE><ADI/><YAS>1</YAS><DOGUM_TARIHI xsi:type="xsd:string"/><SAGLIK_KARNESI>false</SAGLIK_KARNESI><KISIR>false</KISIR><DAVRANIS/><KUPE>false</KUPE><M_UYGULAMA_TARIHI xsi:type="xsd:string"/><TUR_ADI>Köpek</TUR_ADI><IRK_ADI>Melez</IRK_ADI><HAYVAN_MIZAC_ADI/><ANA_RENK>Siyah</ANA_RENK><TALI_RENK_1>Kahverengi</TALI_RENK_1><TALI_RENK_2/><ISARETLEME_ADI>YOK</ISARETLEME_ADI><GELIS_SEKLI_ADI/><CINSIYET_ADI>Erkek</CINSIYET_ADI><ISLEM_TARIHI>2019-12-23T15:29:32</ISLEM_TARIHI></VETNET_TABLE><VETNET_TABLE><ADI/><YAS>1</YAS><DOGUM_TARIHI xsi:type="xsd:dateTime">2018-11-29T00:00:00</DOGUM_TARIHI><SAGLIK_KARNESI>false</SAGLIK_KARNESI><KISIR>true</KISIR><DAVRANIS/><KUPE>false</KUPE><M_UYGULAMA_TARIHI xsi:type="xsd:string"/><TUR_ADI>Köpek</TUR_ADI><IRK_ADI>Melez</IRK_ADI><HAYVAN_MIZAC_ADI/><ANA_RENK>Kahverengi</ANA_RENK><TALI_RENK_1>Kahverengi</TALI_RENK_1><TALI_RENK_2/><ISARETLEME_ADI>YOK</ISARETLEME_ADI><GELIS_SEKLI_ADI/><CINSIYET_ADI>Disi</CINSIYET_ADI><ISLEM_TARIHI>2019-12-09T11:31:45</ISLEM_TARIHI></VETNET_TABLE><VETNET_TABLE><ADI/><YAS>2</YAS><DOGUM_TARIHI xsi:type="xsd:string"/><SAGLIK_KARNESI>false</SAGLIK_KARNESI><KISIR>true</KISIR><DAVRANIS/><KUPE>false</KUPE><M_UYGULAMA_TARIHI xsi:type="xsd:string"/><TUR_ADI>Köpek</TUR_ADI><IRK_ADI>Melez</IRK_ADI><HAYVAN_MIZAC_ADI/><ANA_RENK>Kahverengi</ANA_RENK><TALI_RENK_1>Kahverengi</TALI_RENK_1><TALI_RENK_2/><ISARETLEME_ADI>YOK</ISARETLEME_ADI><GELIS_SEKLI_ADI/><CINSIYET_ADI>Erkek</CINSIYET_ADI><ISLEM_TARIHI>2019-12-16T09:09:36</ISLEM_TARIHI></VETNET_TABLE><VETNET_TABLE><ADI/><YAS>3</YAS><DOGUM_TARIHI xsi:type="xsd:string"/><SAGLIK_KARNESI>false</SAGLIK_KARNESI><KISIR>true</KISIR><DAVRANIS/><KUPE>false</KUPE><M_UYGULAMA_TARIHI xsi:type="xsd:dateTime">2019-11-29T00:00:00</M_UYGULAMA_TARIHI><TUR_ADI>Köpek</TUR_ADI><IRK_ADI>Melez</IRK_ADI><HAYVAN_MIZAC_ADI/><ANA_RENK>Sarı</ANA_RENK><TALI_RENK_1>Boz</TALI_RENK_1><TALI_RENK_2/><ISARETLEME_ADI>TATOO</ISARETLEME_ADI><GELIS_SEKLI_ADI/><CINSIYET_ADI>Erkek</CINSIYET_ADI><ISLEM_TARIHI>2019-12-08T11:47:18</ISLEM_TARIHI></VETNET_TABLE><VETNET_TABLE><ADI/><YAS>1</YAS><DOGUM_TARIHI xsi:type="xsd:string"/><SAGLIK_KARNESI>false</SAGLIK_KARNESI><KISIR>true</KISIR><DAVRANIS/><KUPE>false</KUPE><M_UYGULAMA_TARIHI xsi:type="xsd:string"/><TUR_ADI>Köpek</TUR_ADI><IRK_ADI>Melez</IRK_ADI><HAYVAN_MIZAC_ADI/><ANA_RENK>Siyah</ANA_RENK><TALI_RENK_1>Kahverengi</TALI_RENK_1><TALI_RENK_2/><ISARETLEME_ADI>YOK</ISARETLEME_ADI><GELIS_SEKLI_ADI/><CINSIYET_ADI>Erkek</CINSIYET_ADI><ISLEM_TARIHI>2019-12-08T11:47:22</ISLEM_TARIHI></VETNET_TABLE><VETNET_TABLE><ADI/><YAS>4</YAS><DOGUM_TARIHI xsi:type="xsd:dateTime">2016-01-01T00:00:00</DOGUM_TARIHI><SAGLIK_KARNESI>false</SAGLIK_KARNESI><KISIR>true</KISIR><DAVRANIS/><KUPE>false</KUPE><M_UYGULAMA_TARIHI xsi:type="xsd:dateTime">2019-12-02T00:00:00</M_UYGULAMA_TARIHI><TUR_ADI>Köpek</TUR_ADI><IRK_ADI>Alman Kurt Köpeği</IRK_ADI><HAYVAN_MIZAC_ADI/><ANA_RENK>Siyah</ANA_RENK><TALI_RENK_1>Kahverengi</TALI_RENK_1><TALI_RENK_2/><ISARETLEME_ADI>YOK</ISARETLEME_ADI><GELIS_SEKLI_ADI>Teslim</GELIS_SEKLI_ADI><CINSIYET_ADI>Erkek</CINSIYET_ADI><ISLEM_TARIHI>2019-12-10T12:18:11</ISLEM_TARIHI></VETNET_TABLE><VETNET_TABLE><ADI/><YAS>2</YAS><DOGUM_TARIHI xsi:type="xsd:dateTime">2017-01-01T00:00:00</DOGUM_TARIHI><SAGLIK_KARNESI>false</SAGLIK_KARNESI><KISIR>true</KISIR><DAVRANIS>Uysal</DAVRANIS><KUPE>false</KUPE><M_UYGULAMA_TARIHI xsi:type="xsd:dateTime">2019-12-02T00:00:00</M_UYGULAMA_TARIHI><TUR_ADI>Köpek</TUR_ADI><IRK_ADI>Melez</IRK_ADI><HAYVAN_MIZAC_ADI/><ANA_RENK>Boz</ANA_RENK><TALI_RENK_1>Boz</TALI_RENK_1><TALI_RENK_2/><ISARETLEME_ADI>YOK</ISARETLEME_ADI><GELIS_SEKLI_ADI>Bayıltarak</GELIS_SEKLI_ADI><CINSIYET_ADI>Disi</CINSIYET_ADI><ISLEM_TARIHI>2019-12-13T15:43:54</ISLEM_TARIHI></VETNET_TABLE><VETNET_TABLE><ADI/><YAS>2</YAS><DOGUM_TARIHI xsi:type="xsd:dateTime">2017-01-01T00:00:00</DOGUM_TARIHI><SAGLIK_KARNESI>false</SAGLIK_KARNESI><KISIR>true</KISIR><DAVRANIS>Uysal</DAVRANIS><KUPE>false</KUPE><M_UYGULAMA_TARIHI xsi:type="xsd:dateTime">2019-12-02T00:00:00</M_UYGULAMA_TARIHI><TUR_ADI>Köpek</TUR_ADI><IRK_ADI>Melez</IRK_ADI><HAYVAN_MIZAC_ADI/><ANA_RENK>Sarı</ANA_RENK><TALI_RENK_1>Sarı</TALI_RENK_1><TALI_RENK_2/><ISARETLEME_ADI>YOK</ISARETLEME_ADI><GELIS_SEKLI_ADI>Bayıltarak</GELIS_SEKLI_ADI><CINSIYET_ADI>Disi</CINSIYET_ADI><ISLEM_TARIHI>2019-12-12T15:53:05</ISLEM_TARIHI></VETNET_TABLE><VETNET_TABLE><ADI/><YAS>2</YAS><DOGUM_TARIHI xsi:type="xsd:string"/><SAGLIK_KARNESI>false</SAGLIK_KARNESI><KISIR>false</KISIR><DAVRANIS>sakin</DAVRANIS><KUPE>false</KUPE><M_UYGULAMA_TARIHI xsi:type="xsd:dateTime">2019-11-22T00:00:00</M_UYGULAMA_TARIHI><TUR_ADI>Köpek</TUR_ADI><IRK_ADI>Melez</IRK_ADI><HAYVAN_MIZAC_ADI/><ANA_RENK>Sarı</ANA_RENK><TALI_RENK_1>Siyah</TALI_RENK_1><TALI_RENK_2/><ISARETLEME_ADI>YOK</ISARETLEME_ADI><GELIS_SEKLI_ADI/><CINSIYET_ADI>Disi</CINSIYET_ADI><ISLEM_TARIHI>2019-12-02T14:37:09</ISLEM_TARIHI></VETNET_TABLE><VETNET_TABLE><ADI/><YAS>1</YAS><DOGUM_TARIHI xsi:type="xsd:dateTime">2019-06-03T00:00:00</DOGUM_TARIHI><SAGLIK_KARNESI>false</SAGLIK_KARNESI><KISIR>true</KISIR><DAVRANIS/><KUPE>false</KUPE><M_UYGULAMA_TARIHI xsi:type="xsd:dateTime">2019-12-03T00:00:00</M_UYGULAMA_TARIHI><TUR_ADI>Köpek</TUR_ADI><IRK_ADI>Melez</IRK_ADI><HAYVAN_MIZAC_ADI/><ANA_RENK>Siyah</ANA_RENK><TALI_RENK_1>Beyaz</TALI_RENK_1><TALI_RENK_2/><ISARETLEME_ADI>YOK</ISARETLEME_ADI><GELIS_SEKLI_ADI/><CINSIYET_ADI>Erkek</CINSIYET_ADI><ISLEM_TARIHI>2019-12-12T10:25:34</ISLEM_TARIHI></VETNET_TABLE><VETNET_TABLE><ADI/><YAS>1</YAS><DOGUM_TARIHI xsi:type="xsd:string"/><SAGLIK_KARNESI>false</SAGLIK_KARNESI><KISIR>false</KISIR><DAVRANIS/><KUPE>false</KUPE><M_UYGULAMA_TARIHI xsi:type="xsd:string"/><TUR_ADI>Kedi</TUR_ADI><IRK_ADI>Melez</IRK_ADI><HAYVAN_MIZAC_ADI/><ANA_RENK>Beyaz</ANA_RENK><TALI_RENK_1>Beyaz</TALI_RENK_1><TALI_RENK_2/><ISARETLEME_ADI>YOK</ISARETLEME_ADI><GELIS_SEKLI_ADI/><CINSIYET_ADI>Erkek</CINSIYET_ADI><ISLEM_TARIHI>2019-12-06T09:01:58</ISLEM_TARIHI></VETNET_TABLE><VETNET_TABLE><ADI/><YAS>1</YAS><DOGUM_TARIHI xsi:type="xsd:string"/><SAGLIK_KARNESI>false</SAGLIK_KARNESI><KISIR>false</KISIR><DAVRANIS/><KUPE>false</KUPE><M_UYGULAMA_TARIHI xsi:type="xsd:string"/><TUR_ADI>Köpek</TUR_ADI><IRK_ADI>Jack Russell Terrier</IRK_ADI><HAYVAN_MIZAC_ADI/><ANA_RENK>Beyaz</ANA_RENK><TALI_RENK_1>Kahverengi</TALI_RENK_1><TALI_RENK_2/><ISARETLEME_ADI>YOK</ISARETLEME_ADI><GELIS_SEKLI_ADI/><CINSIYET_ADI>Erkek</CINSIYET_ADI><ISLEM_TARIHI>2019-12-07T12:21:47</ISLEM_TARIHI></VETNET_TABLE><VETNET_TABLE><ADI/><YAS>1</YAS><DOGUM_TARIHI xsi:type="xsd:string"/><SAGLIK_KARNESI>false</SAGLIK_KARNESI><KISIR>true</KISIR><DAVRANIS/><KUPE>false</KUPE><M_UYGULAMA_TARIHI xsi:type="xsd:string"/><TUR_ADI>Köpek</TUR_ADI><IRK_ADI>Melez</IRK_ADI><HAYVAN_MIZAC_ADI/><ANA_RENK>Sarı</ANA_RENK><TALI_RENK_1>Beyaz</TALI_RENK_1><TALI_RENK_2/><ISARETLEME_ADI>YOK</ISARETLEME_ADI><GELIS_SEKLI_ADI/><CINSIYET_ADI>Erkek</CINSIYET_ADI><ISLEM_TARIHI>2020-01-10T10:45:07</ISLEM_TARIHI></VETNET_TABLE><VETNET_TABLE><ADI/><YAS>1</YAS><DOGUM_TARIHI xsi:type="xsd:string"/><SAGLIK_KARNESI>false</SAGLIK_KARNESI><KISIR>false</KISIR><DAVRANIS/><KUPE>false</KUPE><M_UYGULAMA_TARIHI xsi:type="xsd:string"/><TUR_ADI>Köpek</TUR_ADI><IRK_ADI>Golden Retriever</IRK_ADI><HAYVAN_MIZAC_ADI/><ANA_RENK>Sarı</ANA_RENK><TALI_RENK_1>Sarı</TALI_RENK_1><TALI_RENK_2/><ISARETLEME_ADI>YOK</ISARETLEME_ADI><GELIS_SEKLI_ADI/><CINSIYET_ADI>Disi</CINSIYET_ADI><ISLEM_TARIHI>2019-12-17T13:54:11</ISLEM_TARIHI></VETNET_TABLE><VETNET_TABLE><ADI/><YAS>1</YAS><DOGUM_TARIHI xsi:type="xsd:string"/><SAGLIK_KARNESI>false</SAGLIK_KARNESI><KISIR>false</KISIR><DAVRANIS/><KUPE>false</KUPE><M_UYGULAMA_TARIHI xsi:type="xsd:string"/><TUR_ADI>Köpek</TUR_ADI><IRK_ADI>Melez</IRK_ADI><HAYVAN_MIZAC_ADI/><ANA_RENK>Siyah</ANA_RENK><TALI_RENK_1>Kahverengi</TALI_RENK_1><TALI_RENK_2/><ISARETLEME_ADI>YOK</ISARETLEME_ADI><GELIS_SEKLI_ADI/><CINSIYET_ADI>Erkek</CINSIYET_ADI><ISLEM_TARIHI>2019-12-10T14:32:43</ISLEM_TARIHI></VETNET_TABLE><VETNET_TABLE><ADI>neşeli</ADI><YAS>1</YAS><DOGUM_TARIHI xsi:type="xsd:dateTime">2019-01-01T00:00:00</DOGUM_TARIHI><SAGLIK_KARNESI>false</SAGLIK_KARNESI><KISIR>false</KISIR><DAVRANIS>uysal</DAVRANIS><KUPE>false</KUPE><M_UYGULAMA_TARIHI xsi:type="xsd:dateTime">2019-12-09T00:00:00</M_UYGULAMA_TARIHI><TUR_ADI>Köpek</TUR_ADI><IRK_ADI>Melez</IRK_ADI><HAYVAN_MIZAC_ADI/><ANA_RENK>Gri</ANA_RENK><TALI_RENK_1>Beyaz</TALI_RENK_1><TALI_RENK_2/><ISARETLEME_ADI>YOK</ISARETLEME_ADI><GELIS_SEKLI_ADI/><CINSIYET_ADI>Erkek</CINSIYET_ADI><ISLEM_TARIHI>2019-12-12T15:04:44</ISLEM_TARIHI></VETNET_TABLE><VETNET_TABLE><ADI>PAMUK</ADI><YAS>1</YAS><DOGUM_TARIHI xsi:type="xsd:dateTime">2019-09-01T00:00:00</DOGUM_TARIHI><SAGLIK_KARNESI>false</SAGLIK_KARNESI><KISIR>false</KISIR><DAVRANIS>UYSAL</DAVRANIS><KUPE>false</KUPE><M_UYGULAMA_TARIHI xsi:type="xsd:dateTime">2019-12-05T00:00:00</M_UYGULAMA_TARIHI><TUR_ADI>Kedi</TUR_ADI><IRK_ADI>Tekir</IRK_ADI><HAYVAN_MIZAC_ADI/><ANA_RENK>Siyah</ANA_RENK><TALI_RENK_1>Beyaz</TALI_RENK_1><TALI_RENK_2>Sarı</TALI_RENK_2><ISARETLEME_ADI>YOK</ISARETLEME_ADI><GELIS_SEKLI_ADI/><CINSIYET_ADI>Disi</CINSIYET_ADI><ISLEM_TARIHI>2019-12-12T15:00:23</ISLEM_TARIHI></VETNET_TABLE><VETNET_TABLE><ADI>TARÇIN</ADI><YAS>1</YAS><DOGUM_TARIHI xsi:type="xsd:dateTime">2019-01-01T00:00:00</DOGUM_TARIHI><SAGLIK_KARNESI>false</SAGLIK_KARNESI><KISIR>true</KISIR><DAVRANIS/><KUPE>false</KUPE><M_UYGULAMA_TARIHI xsi:type="xsd:string"/><TUR_ADI>Kedi</TUR_ADI><IRK_ADI>Tekir</IRK_ADI><HAYVAN_MIZAC_ADI/><ANA_RENK>Kahverengi</ANA_RENK><TALI_RENK_1>Beyaz</TALI_RENK_1><TALI_RENK_2/><ISARETLEME_ADI>YOK</ISARETLEME_ADI><GELIS_SEKLI_ADI/><CINSIYET_ADI>Erkek</CINSIYET_ADI><ISLEM_TARIHI>2019-12-12T14:56:48</ISLEM_TARIHI></VETNET_TABLE><VETNET_TABLE><ADI>MESTAN</ADI><YAS>1</YAS><DOGUM_TARIHI xsi:type="xsd:dateTime">2019-01-01T00:00:00</DOGUM_TARIHI><SAGLIK_KARNESI>false</SAGLIK_KARNESI><KISIR>true</KISIR><DAVRANIS>UYSAL</DAVRANIS><KUPE>false</KUPE><M_UYGULAMA_TARIHI xsi:type="xsd:dateTime">2019-11-28T00:00:00</M_UYGULAMA_TARIHI><TUR_ADI>Kedi</TUR_ADI><IRK_ADI>Tekir</IRK_ADI><HAYVAN_MIZAC_ADI/><ANA_RENK>Siyah</ANA_RENK><TALI_RENK_1>Beyaz</TALI_RENK_1><TALI_RENK_2/><ISARETLEME_ADI>YOK</ISARETLEME_ADI><GELIS_SEKLI_ADI>Teslim</GELIS_SEKLI_ADI><CINSIYET_ADI>Erkek</CINSIYET_ADI><ISLEM_TARIHI>2019-12-12T14:50:52</ISLEM_TARIHI></VETNET_TABLE><VETNET_TABLE><ADI/><YAS>1</YAS><DOGUM_TARIHI xsi:type="xsd:string"/><SAGLIK_KARNESI>false</SAGLIK_KARNESI><KISIR>true</KISIR><DAVRANIS/><KUPE>false</KUPE><M_UYGULAMA_TARIHI xsi:type="xsd:string"/><TUR_ADI>Köpek</TUR_ADI><IRK_ADI>Melez</IRK_ADI><HAYVAN_MIZAC_ADI/><ANA_RENK>Siyah</ANA_RENK><TALI_RENK_1>Kahverengi</TALI_RENK_1><TALI_RENK_2/><ISARETLEME_ADI>YOK</ISARETLEME_ADI><GELIS_SEKLI_ADI/><CINSIYET_ADI>Disi</CINSIYET_ADI><ISLEM_TARIHI>2020-01-20T10:19:40</ISLEM_TARIHI></VETNET_TABLE><VETNET_TABLE><ADI/><YAS>1</YAS><DOGUM_TARIHI xsi:type="xsd:string"/><SAGLIK_KARNESI>false</SAGLIK_KARNESI><KISIR>false</KISIR><DAVRANIS/><KUPE>false</KUPE><M_UYGULAMA_TARIHI xsi:type="xsd:string"/><TUR_ADI>Kedi</TUR_ADI><IRK_ADI>Melez</IRK_ADI><HAYVAN_MIZAC_ADI/><ANA_RENK>Tekir</ANA_RENK><TALI_RENK_1>Beyaz</TALI_RENK_1><TALI_RENK_2/><ISARETLEME_ADI>YOK</ISARETLEME_ADI><GELIS_SEKLI_ADI/><CINSIYET_ADI>Erkek</CINSIYET_ADI><ISLEM_TARIHI>2019-12-17T13:54:19</ISLEM_TARIHI></VETNET_TABLE><VETNET_TABLE><ADI/><YAS>5</YAS><DOGUM_TARIHI xsi:type="xsd:string"/><SAGLIK_KARNESI>false</SAGLIK_KARNESI><KISIR>false</KISIR><DAVRANIS/><KUPE>false</KUPE><M_UYGULAMA_TARIHI xsi:type="xsd:string"/><TUR_ADI>Köpek</TUR_ADI><IRK_ADI>Melez</IRK_ADI><HAYVAN_MIZAC_ADI/><ANA_RENK>Kahverengi</ANA_RENK><TALI_RENK_1>Kahverengi</TALI_RENK_1><TALI_RENK_2/><ISARETLEME_ADI>YOK</ISARETLEME_ADI><GELIS_SEKLI_ADI/><CINSIYET_ADI>Disi</CINSIYET_ADI><ISLEM_TARIHI>2019-12-16T13:38:38</ISLEM_TARIHI></VETNET_TABLE><VETNET_TABLE><ADI/><YAS>4</YAS><DOGUM_TARIHI xsi:type="xsd:dateTime">2015-01-01T00:00:00</DOGUM_TARIHI><SAGLIK_KARNESI>false</SAGLIK_KARNESI><KISIR>true</KISIR><DAVRANIS>Uysal</DAVRANIS><KUPE>false</KUPE><M_UYGULAMA_TARIHI xsi:type="xsd:dateTime">2019-12-11T00:00:00</M_UYGULAMA_TARIHI><TUR_ADI>Köpek</TUR_ADI><IRK_ADI>Melez</IRK_ADI><HAYVAN_MIZAC_ADI/><ANA_RENK>Boz</ANA_RENK><TALI_RENK_1>Boz</TALI_RENK_1><TALI_RENK_2/><ISARETLEME_ADI>YOK</ISARETLEME_ADI><GELIS_SEKLI_ADI>Bayıltarak</GELIS_SEKLI_ADI><CINSIYET_ADI>Disi</CINSIYET_ADI><ISLEM_TARIHI>2019-12-23T09:23:43</ISLEM_TARIHI></VETNET_TABLE><VETNET_TABLE><ADI/><YAS>1</YAS><DOGUM_TARIHI xsi:type="xsd:dateTime">2019-09-01T00:00:00</DOGUM_TARIHI><SAGLIK_KARNESI>false</SAGLIK_KARNESI><KISIR>false</KISIR><DAVRANIS>UYSAL</DAVRANIS><KUPE>false</KUPE><M_UYGULAMA_TARIHI xsi:type="xsd:dateTime">2019-12-11T00:00:00</M_UYGULAMA_TARIHI><TUR_ADI>Kedi</TUR_ADI><IRK_ADI>Tekir</IRK_ADI><HAYVAN_MIZAC_ADI/><ANA_RENK>Siyah</ANA_RENK><TALI_RENK_1>Beyaz</TALI_RENK_1><TALI_RENK_2/><ISARETLEME_ADI>YOK</ISARETLEME_ADI><GELIS_SEKLI_ADI>Teslim</GELIS_SEKLI_ADI><CINSIYET_ADI>Disi</CINSIYET_ADI><ISLEM_TARIHI>2019-12-12T14:47:47</ISLEM_TARIHI></VETNET_TABLE><VETNET_TABLE><ADI/><YAS>2</YAS><DOGUM_TARIHI xsi:type="xsd:string"/><SAGLIK_KARNESI>false</SAGLIK_KARNESI><KISIR>false</KISIR><DAVRANIS/><KUPE>false</KUPE><M_UYGULAMA_TARIHI xsi:type="xsd:string"/><TUR_ADI>Kedi</TUR_ADI><IRK_ADI>Melez</IRK_ADI><HAYVAN_MIZAC_ADI/><ANA_RENK>Sarı</ANA_RENK><TALI_RENK_1>Beyaz</TALI_RENK_1><TALI_RENK_2/><ISARETLEME_ADI>YOK</ISARETLEME_ADI><GELIS_SEKLI_ADI/><CINSIYET_ADI>Disi</CINSIYET_ADI><ISLEM_TARIHI>2019-12-17T13:54:23</ISLEM_TARIHI></VETNET_TABLE><VETNET_TABLE><ADI/><YAS>1</YAS><DOGUM_TARIHI xsi:type="xsd:dateTime">2019-11-20T00:00:00</DOGUM_TARIHI><SAGLIK_KARNESI>false</SAGLIK_KARNESI><KISIR>false</KISIR><DAVRANIS/><KUPE>false</KUPE><M_UYGULAMA_TARIHI xsi:type="xsd:string"/><TUR_ADI>Köpek</TUR_ADI><IRK_ADI>Melez</IRK_ADI><HAYVAN_MIZAC_ADI/><ANA_RENK>Kahverengi</ANA_RENK><TALI_RENK_1>Beyaz</TALI_RENK_1><TALI_RENK_2/><ISARETLEME_ADI>YOK</ISARETLEME_ADI><GELIS_SEKLI_ADI/><CINSIYET_ADI>Erkek</CINSIYET_ADI><ISLEM_TARIHI>2019-12-13T15:57:19</ISLEM_TARIHI></VETNET_TABLE><VETNET_TABLE><ADI>BÜCÜR</ADI><YAS>1</YAS><DOGUM_TARIHI xsi:type="xsd:dateTime">2019-09-01T00:00:00</DOGUM_TARIHI><SAGLIK_KARNESI>false</SAGLIK_KARNESI><KISIR>false</KISIR><DAVRANIS>UYSAL</DAVRANIS><KUPE>false</KUPE><M_UYGULAMA_TARIHI xsi:type="xsd:string"/><TUR_ADI>Köpek</TUR_ADI><IRK_ADI>Melez</IRK_ADI><HAYVAN_MIZAC_ADI/><ANA_RENK>Kahverengi</ANA_RENK><TALI_RENK_1>Beyaz</TALI_RENK_1><TALI_RENK_2/><ISARETLEME_ADI>YOK</ISARETLEME_ADI><GELIS_SEKLI_ADI>Teslim</GELIS_SEKLI_ADI><CINSIYET_ADI>Erkek</CINSIYET_ADI><ISLEM_TARIHI>2019-12-16T10:47:05</ISLEM_TARIHI></VETNET_TABLE><VETNET_TABLE><ADI>KORSAN</ADI><YAS>1</YAS><DOGUM_TARIHI xsi:type="xsd:dateTime">2019-11-01T00:00:00</DOGUM_TARIHI><SAGLIK_KARNESI>false</SAGLIK_KARNESI><KISIR>false</KISIR><DAVRANIS>UYSAL</DAVRANIS><KUPE>false</KUPE><M_UYGULAMA_TARIHI xsi:type="xsd:string"/><TUR_ADI>Köpek</TUR_ADI><IRK_ADI>Melez</IRK_ADI><HAYVAN_MIZAC_ADI/><ANA_RENK>Kahverengi</ANA_RENK><TALI_RENK_1>Beyaz</TALI_RENK_1><TALI_RENK_2/><ISARETLEME_ADI>YOK</ISARETLEME_ADI><GELIS_SEKLI_ADI/><CINSIYET_ADI>Erkek</CINSIYET_ADI><ISLEM_TARIHI>2019-12-16T10:41:38</ISLEM_TARIHI></VETNET_TABLE><VETNET_TABLE><ADI>CESUR</ADI><YAS>1</YAS><DOGUM_TARIHI xsi:type="xsd:dateTime">2019-11-11T00:00:00</DOGUM_TARIHI><SAGLIK_KARNESI>false</SAGLIK_KARNESI><KISIR>false</KISIR><DAVRANIS>UYSAL</DAVRANIS><KUPE>false</KUPE><M_UYGULAMA_TARIHI xsi:type="xsd:string"/><TUR_ADI>Köpek</TUR_ADI><IRK_ADI>Melez</IRK_ADI><HAYVAN_MIZAC_ADI/><ANA_RENK>Kahverengi</ANA_RENK><TALI_RENK_1>Beyaz</TALI_RENK_1><TALI_RENK_2/><ISARETLEME_ADI>YOK</ISARETLEME_ADI><GELIS_SEKLI_ADI>Teslim</GELIS_SEKLI_ADI><CINSIYET_ADI>Erkek</CINSIYET_ADI><ISLEM_TARIHI>2019-12-16T10:34:18</ISLEM_TARIHI></VETNET_TABLE><VETNET_TABLE><ADI/><YAS>1</YAS><DOGUM_TARIHI xsi:type="xsd:dateTime">2019-11-10T00:00:00</DOGUM_TARIHI><SAGLIK_KARNESI>false</SAGLIK_KARNESI><KISIR>false</KISIR><DAVRANIS>UYSAL</DAVRANIS><KUPE>false</KUPE><M_UYGULAMA_TARIHI xsi:type="xsd:string"/><TUR_ADI>Köpek</TUR_ADI><IRK_ADI>Melez</IRK_ADI><HAYVAN_MIZAC_ADI/><ANA_RENK>Kahverengi</ANA_RENK><TALI_RENK_1>Kahverengi</TALI_RENK_1><TALI_RENK_2/><ISARETLEME_ADI>YOK</ISARETLEME_ADI><GELIS_SEKLI_ADI>Teslim</GELIS_SEKLI_ADI><CINSIYET_ADI>Disi</CINSIYET_ADI><ISLEM_TARIHI>2019-12-16T10:15:31</ISLEM_TARIHI></VETNET_TABLE><VETNET_TABLE><ADI>ÇOMAR</ADI><YAS>1</YAS><DOGUM_TARIHI xsi:type="xsd:dateTime">2019-11-11T00:00:00</DOGUM_TARIHI><SAGLIK_KARNESI>false</SAGLIK_KARNESI><KISIR>false</KISIR><DAVRANIS>UYSAL</DAVRANIS><KUPE>false</KUPE><M_UYGULAMA_TARIHI xsi:type="xsd:string"/><TUR_ADI>Köpek</TUR_ADI><IRK_ADI>Melez</IRK_ADI><HAYVAN_MIZAC_ADI/><ANA_RENK>Kahverengi</ANA_RENK><TALI_RENK_1>Kahverengi</TALI_RENK_1><TALI_RENK_2/><ISARETLEME_ADI>YOK</ISARETLEME_ADI><GELIS_SEKLI_ADI>Yakalanarak</GELIS_SEKLI_ADI><CINSIYET_ADI>Disi</CINSIYET_ADI><ISLEM_TARIHI>2019-12-16T10:06:24</ISLEM_TARIHI></VETNET_TABLE><VETNET_TABLE><ADI>ÇOMAR</ADI><YAS>1</YAS><DOGUM_TARIHI xsi:type="xsd:dateTime">2019-11-11T00:00:00</DOGUM_TARIHI><SAGLIK_KARNESI>false</SAGLIK_KARNESI><KISIR>false</KISIR><DAVRANIS>UYSAL</DAVRANIS><KUPE>false</KUPE><M_UYGULAMA_TARIHI xsi:type="xsd:string"/><TUR_ADI>Köpek</TUR_ADI><IRK_ADI>Melez</IRK_ADI><HAYVAN_MIZAC_ADI/><ANA_RENK>Kahverengi</ANA_RENK><TALI_RENK_1>Kahverengi</TALI_RENK_1><TALI_RENK_2/><ISARETLEME_ADI>YOK</ISARETLEME_ADI><GELIS_SEKLI_ADI>Yakalanarak</GELIS_SEKLI_ADI><CINSIYET_ADI>Disi</CINSIYET_ADI><ISLEM_TARIHI>2019-12-16T10:06:19</ISLEM_TARIHI></VETNET_TABLE><VETNET_TABLE><ADI>DUMAN</ADI><YAS>1</YAS><DOGUM_TARIHI xsi:type="xsd:dateTime">2019-09-01T00:00:00</DOGUM_TARIHI><SAGLIK_KARNESI>false</SAGLIK_KARNESI><KISIR>false</KISIR><DAVRANIS>UYSAL</DAVRANIS><KUPE>false</KUPE><M_UYGULAMA_TARIHI xsi:type="xsd:string"/><TUR_ADI>Köpek</TUR_ADI><IRK_ADI>Melez</IRK_ADI><HAYVAN_MIZAC_ADI/><ANA_RENK>Boz</ANA_RENK><TALI_RENK_1>Boz</TALI_RENK_1><TALI_RENK_2/><ISARETLEME_ADI>YOK</ISARETLEME_ADI><GELIS_SEKLI_ADI>Teslim</GELIS_SEKLI_ADI><CINSIYET_ADI>Erkek</CINSIYET_ADI><ISLEM_TARIHI>2019-12-16T09:33:27</ISLEM_TARIHI></VETNET_TABLE><VETNET_TABLE><ADI>ROKU</ADI><YAS>1</YAS><DOGUM_TARIHI xsi:type="xsd:dateTime">2019-08-01T00:00:00</DOGUM_TARIHI><SAGLIK_KARNESI>false</SAGLIK_KARNESI><KISIR>false</KISIR><DAVRANIS>UYSAL</DAVRANIS><KUPE>false</KUPE><M_UYGULAMA_TARIHI xsi:type="xsd:string"/><TUR_ADI>Köpek</TUR_ADI><IRK_ADI>Melez</IRK_ADI><HAYVAN_MIZAC_ADI/><ANA_RENK>Boz</ANA_RENK><TALI_RENK_1>Boz</TALI_RENK_1><TALI_RENK_2/><ISARETLEME_ADI>YOK</ISARETLEME_ADI><GELIS_SEKLI_ADI/><CINSIYET_ADI>Erkek</CINSIYET_ADI><ISLEM_TARIHI>2019-12-16T09:30:03</ISLEM_TARIHI></VETNET_TABLE><VETNET_TABLE><ADI/><YAS>2</YAS><DOGUM_TARIHI xsi:type="xsd:string"/><SAGLIK_KARNESI>false</SAGLIK_KARNESI><KISIR>false</KISIR><DAVRANIS/><KUPE>false</KUPE><M_UYGULAMA_TARIHI xsi:type="xsd:string"/><TUR_ADI>Kedi</TUR_ADI><IRK_ADI>Melez</IRK_ADI><HAYVAN_MIZAC_ADI/><ANA_RENK>Siyah</ANA_RENK><TALI_RENK_1>Siyah</TALI_RENK_1><TALI_RENK_2/><ISARETLEME_ADI>YOK</ISARETLEME_ADI><GELIS_SEKLI_ADI/><CINSIYET_ADI>Erkek</CINSIYET_ADI><ISLEM_TARIHI>2019-12-15T13:36:41</ISLEM_TARIHI></VETNET_TABLE><VETNET_TABLE><ADI/><YAS>10</YAS><DOGUM_TARIHI xsi:type="xsd:dateTime">2010-01-01T00:00:00</DOGUM_TARIHI><SAGLIK_KARNESI>false</SAGLIK_KARNESI><KISIR>false</KISIR><DAVRANIS/><KUPE>false</KUPE><M_UYGULAMA_TARIHI xsi:type="xsd:string"/><TUR_ADI>Köpek</TUR_ADI><IRK_ADI>Rottweiler</IRK_ADI><HAYVAN_MIZAC_ADI/><ANA_RENK>Siyah</ANA_RENK><TALI_RENK_1>Kahverengi</TALI_RENK_1><TALI_RENK_2/><ISARETLEME_ADI>YOK</ISARETLEME_ADI><GELIS_SEKLI_ADI/><CINSIYET_ADI>Erkek</CINSIYET_ADI><ISLEM_TARIHI>2019-12-16T16:53:10</ISLEM_TARIHI></VETNET_TABLE><VETNET_TABLE><ADI/><YAS>10</YAS><DOGUM_TARIHI xsi:type="xsd:dateTime">2010-01-01T00:00:00</DOGUM_TARIHI><SAGLIK_KARNESI>false</SAGLIK_KARNESI><KISIR>false</KISIR><DAVRANIS/><KUPE>false</KUPE><M_UYGULAMA_TARIHI xsi:type="xsd:string"/><TUR_ADI>Köpek</TUR_ADI><IRK_ADI>Rottweiler</IRK_ADI><HAYVAN_MIZAC_ADI/><ANA_RENK>Siyah</ANA_RENK><TALI_RENK_1>Kahverengi</TALI_RENK_1><TALI_RENK_2/><ISARETLEME_ADI>YOK</ISARETLEME_ADI><GELIS_SEKLI_ADI/><CINSIYET_ADI>Erkek</CINSIYET_ADI><ISLEM_TARIHI>2019-12-16T16:53:14</ISLEM_TARIHI></VETNET_TABLE><VETNET_TABLE><ADI/><YAS>1</YAS><DOGUM_TARIHI xsi:type="xsd:string"/><SAGLIK_KARNESI>false</SAGLIK_KARNESI><KISIR>false</KISIR><DAVRANIS/><KUPE>false</KUPE><M_UYGULAMA_TARIHI xsi:type="xsd:dateTime">2019-12-15T00:00:00</M_UYGULAMA_TARIHI><TUR_ADI>Köpek</TUR_ADI><IRK_ADI>Melez</IRK_ADI><HAYVAN_MIZAC_ADI/><ANA_RENK>Siyah</ANA_RENK><TALI_RENK_1>Kahverengi</TALI_RENK_1><TALI_RENK_2/><ISARETLEME_ADI>YOK</ISARETLEME_ADI><GELIS_SEKLI_ADI>Teslim</GELIS_SEKLI_ADI><CINSIYET_ADI>Disi</CINSIYET_ADI><ISLEM_TARIHI>2020-01-29T16:29:43</ISLEM_TARIHI></VETNET_TABLE><VETNET_TABLE><ADI/><YAS>1</YAS><DOGUM_TARIHI xsi:type="xsd:string"/><SAGLIK_KARNESI>false</SAGLIK_KARNESI><KISIR>false</KISIR><DAVRANIS/><KUPE>false</KUPE><M_UYGULAMA_TARIHI xsi:type="xsd:string"/><TUR_ADI>Kedi</TUR_ADI><IRK_ADI>Scottish Fold</IRK_ADI><HAYVAN_MIZAC_ADI/><ANA_RENK>Gri</ANA_RENK><TALI_RENK_1>Boz</TALI_RENK_1><TALI_RENK_2/><ISARETLEME_ADI>YOK</ISARETLEME_ADI><GELIS_SEKLI_ADI/><CINSIYET_ADI>Disi</CINSIYET_ADI><ISLEM_TARIHI>2019-12-19T15:54:34</ISLEM_TARIHI></VETNET_TABLE><VETNET_TABLE><ADI>LİMON</ADI><YAS>1</YAS><DOGUM_TARIHI xsi:type="xsd:dateTime">2018-12-01T00:00:00</DOGUM_TARIHI><SAGLIK_KARNESI>false</SAGLIK_KARNESI><KISIR>true</KISIR><DAVRANIS>UYSAL</DAVRANIS><KUPE>false</KUPE><M_UYGULAMA_TARIHI xsi:type="xsd:dateTime">2019-12-13T00:00:00</M_UYGULAMA_TARIHI><TUR_ADI>Kedi</TUR_ADI><IRK_ADI>Tekir</IRK_ADI><HAYVAN_MIZAC_ADI/><ANA_RENK>Sarı</ANA_RENK><TALI_RENK_1>Sarı</TALI_RENK_1><TALI_RENK_2/><ISARETLEME_ADI>YOK</ISARETLEME_ADI><GELIS_SEKLI_ADI/><CINSIYET_ADI>Erkek</CINSIYET_ADI><ISLEM_TARIHI>2019-12-23T10:12:41</ISLEM_TARIHI></VETNET_TABLE><VETNET_TABLE><ADI/><YAS>2</YAS><DOGUM_TARIHI xsi:type="xsd:dateTime">2017-01-01T00:00:00</DOGUM_TARIHI><SAGLIK_KARNESI>false</SAGLIK_KARNESI><KISIR>true</KISIR><DAVRANIS>Uysal</DAVRANIS><KUPE>false</KUPE><M_UYGULAMA_TARIHI xsi:type="xsd:dateTime">2019-12-23T00:00:00</M_UYGULAMA_TARIHI><TUR_ADI>Köpek</TUR_ADI><IRK_ADI>Melez</IRK_ADI><HAYVAN_MIZAC_ADI/><ANA_RENK>Siyah</ANA_RENK><TALI_RENK_1>Beyaz</TALI_RENK_1><TALI_RENK_2/><ISARETLEME_ADI>YOK</ISARETLEME_ADI><GELIS_SEKLI_ADI>Bayıltarak</GELIS_SEKLI_ADI><CINSIYET_ADI>Disi</CINSIYET_ADI><ISLEM_TARIHI>2020-01-07T15:03:47</ISLEM_TARIHI></VETNET_TABLE><VETNET_TABLE><ADI/><YAS>2</YAS><DOGUM_TARIHI xsi:type="xsd:dateTime">2017-01-01T00:00:00</DOGUM_TARIHI><SAGLIK_KARNESI>false</SAGLIK_KARNESI><KISIR>true</KISIR><DAVRANIS>Uysal</DAVRANIS><KUPE>false</KUPE><M_UYGULAMA_TARIHI xsi:type="xsd:dateTime">2019-12-23T00:00:00</M_UYGULAMA_TARIHI><TUR_ADI>Köpek</TUR_ADI><IRK_ADI>Melez</IRK_ADI><HAYVAN_MIZAC_ADI/><ANA_RENK>Siyah</ANA_RENK><TALI_RENK_1>Beyaz</TALI_RENK_1><TALI_RENK_2/><ISARETLEME_ADI>YOK</ISARETLEME_ADI><GELIS_SEKLI_ADI>Bayıltarak</GELIS_SEKLI_ADI><CINSIYET_ADI>Disi</CINSIYET_ADI><ISLEM_TARIHI>2020-01-07T15:03:33</ISLEM_TARIHI></VETNET_TABLE><VETNET_TABLE><ADI/><YAS>2</YAS><DOGUM_TARIHI xsi:type="xsd:string"/><SAGLIK_KARNESI>false</SAGLIK_KARNESI><KISIR>false</KISIR><DAVRANIS/><KUPE>false</KUPE><M_UYGULAMA_TARIHI xsi:type="xsd:string"/><TUR_ADI>Köpek</TUR_ADI><IRK_ADI>Pinscher</IRK_ADI><HAYVAN_MIZAC_ADI/><ANA_RENK>Sarı</ANA_RENK><TALI_RENK_1>Sarı</TALI_RENK_1><TALI_RENK_2/><ISARETLEME_ADI>YOK</ISARETLEME_ADI><GELIS_SEKLI_ADI/><CINSIYET_ADI>Disi</CINSIYET_ADI><ISLEM_TARIHI>2019-12-31T13:46:31</ISLEM_TARIHI></VETNET_TABLE><VETNET_TABLE><ADI/><YAS>4</YAS><DOGUM_TARIHI xsi:type="xsd:string"/><SAGLIK_KARNESI>false</SAGLIK_KARNESI><KISIR>true</KISIR><DAVRANIS/><KUPE>false</KUPE><M_UYGULAMA_TARIHI xsi:type="xsd:string"/><TUR_ADI>Köpek</TUR_ADI><IRK_ADI>Melez</IRK_ADI><HAYVAN_MIZAC_ADI/><ANA_RENK>Sarı</ANA_RENK><TALI_RENK_1>Sarı</TALI_RENK_1><TALI_RENK_2/><ISARETLEME_ADI>YOK</ISARETLEME_ADI><GELIS_SEKLI_ADI/><CINSIYET_ADI>Erkek</CINSIYET_ADI><ISLEM_TARIHI>2020-01-17T11:20:02</ISLEM_TARIHI></VETNET_TABLE><VETNET_TABLE><ADI/><YAS>2</YAS><DOGUM_TARIHI xsi:type="xsd:dateTime">2017-01-01T00:00:00</DOGUM_TARIHI><SAGLIK_KARNESI>false</SAGLIK_KARNESI><KISIR>true</KISIR><DAVRANIS>Uysal</DAVRANIS><KUPE>false</KUPE><M_UYGULAMA_TARIHI xsi:type="xsd:dateTime">2019-12-25T00:00:00</M_UYGULAMA_TARIHI><TUR_ADI>Köpek</TUR_ADI><IRK_ADI>Melez</IRK_ADI><HAYVAN_MIZAC_ADI/><ANA_RENK>Beyaz</ANA_RENK><TALI_RENK_1>Gri</TALI_RENK_1><TALI_RENK_2/><ISARETLEME_ADI>YOK</ISARETLEME_ADI><GELIS_SEKLI_ADI>Bayıltarak</GELIS_SEKLI_ADI><CINSIYET_ADI>Disi</CINSIYET_ADI><ISLEM_TARIHI>2019-12-30T09:55:03</ISLEM_TARIHI></VETNET_TABLE><VETNET_TABLE><ADI/><YAS>2</YAS><DOGUM_TARIHI xsi:type="xsd:string"/><SAGLIK_KARNESI>false</SAGLIK_KARNESI><KISIR>true</KISIR><DAVRANIS/><KUPE>false</KUPE><M_UYGULAMA_TARIHI xsi:type="xsd:dateTime">2019-12-26T00:00:00</M_UYGULAMA_TARIHI><TUR_ADI>Köpek</TUR_ADI><IRK_ADI>Terrier</IRK_ADI><HAYVAN_MIZAC_ADI/><ANA_RENK>Beyaz</ANA_RENK><TALI_RENK_1>Beyaz</TALI_RENK_1><TALI_RENK_2/><ISARETLEME_ADI>TATOO</ISARETLEME_ADI><GELIS_SEKLI_ADI>Teslim</GELIS_SEKLI_ADI><CINSIYET_ADI>Erkek</CINSIYET_ADI><ISLEM_TARIHI>2020-01-04T15:30:52</ISLEM_TARIHI></VETNET_TABLE><VETNET_TABLE><ADI/><YAS>1</YAS><DOGUM_TARIHI xsi:type="xsd:string"/><SAGLIK_KARNESI>false</SAGLIK_KARNESI><KISIR>false</KISIR><DAVRANIS/><KUPE>false</KUPE><M_UYGULAMA_TARIHI xsi:type="xsd:string"/><TUR_ADI>Köpek</TUR_ADI><IRK_ADI>Melez</IRK_ADI><HAYVAN_MIZAC_ADI/><ANA_RENK>Siyah</ANA_RENK><TALI_RENK_1>Beyaz</TALI_RENK_1><TALI_RENK_2/><ISARETLEME_ADI>YOK</ISARETLEME_ADI><GELIS_SEKLI_ADI/><CINSIYET_ADI>Disi</CINSIYET_ADI><ISLEM_TARIHI>2019-12-30T08:57:24</ISLEM_TARIHI></VETNET_TABLE><VETNET_TABLE><ADI/><YAS>3</YAS><DOGUM_TARIHI xsi:type="xsd:string"/><SAGLIK_KARNESI>false</SAGLIK_KARNESI><KISIR>true</KISIR><DAVRANIS/><KUPE>false</KUPE><M_UYGULAMA_TARIHI xsi:type="xsd:string"/><TUR_ADI>Kedi</TUR_ADI><IRK_ADI>Melez</IRK_ADI><HAYVAN_MIZAC_ADI/><ANA_RENK>Gri</ANA_RENK><TALI_RENK_1>Gri</TALI_RENK_1><TALI_RENK_2/><ISARETLEME_ADI>YOK</ISARETLEME_ADI><GELIS_SEKLI_ADI/><CINSIYET_ADI>Erkek</CINSIYET_ADI><ISLEM_TARIHI>2020-01-03T11:25:59</ISLEM_TARIHI></VETNET_TABLE><VETNET_TABLE><ADI/><YAS>1</YAS><DOGUM_TARIHI xsi:type="xsd:dateTime">2019-01-01T00:00:00</DOGUM_TARIHI><SAGLIK_KARNESI>false</SAGLIK_KARNESI><KISIR>false</KISIR><DAVRANIS>UYSAL</DAVRANIS><KUPE>false</KUPE><M_UYGULAMA_TARIHI xsi:type="xsd:string"/><TUR_ADI>Köpek</TUR_ADI><IRK_ADI>Melez</IRK_ADI><HAYVAN_MIZAC_ADI/><ANA_RENK>Sarı</ANA_RENK><TALI_RENK_1>Beyaz</TALI_RENK_1><TALI_RENK_2/><ISARETLEME_ADI>YOK</ISARETLEME_ADI><GELIS_SEKLI_ADI/><CINSIYET_ADI>Disi</CINSIYET_ADI><ISLEM_TARIHI>2019-12-30T10:12:06</ISLEM_TARIHI></VETNET_TABLE><VETNET_TABLE><ADI/><YAS>1</YAS><DOGUM_TARIHI xsi:type="xsd:dateTime">2019-01-01T00:00:00</DOGUM_TARIHI><SAGLIK_KARNESI>false</SAGLIK_KARNESI><KISIR>false</KISIR><DAVRANIS/><KUPE>false</KUPE><M_UYGULAMA_TARIHI xsi:type="xsd:string"/><TUR_ADI>Köpek</TUR_ADI><IRK_ADI>Melez</IRK_ADI><HAYVAN_MIZAC_ADI/><ANA_RENK>Sarı</ANA_RENK><TALI_RENK_1>Sarı</TALI_RENK_1><TALI_RENK_2/><ISARETLEME_ADI>YOK</ISARETLEME_ADI><GELIS_SEKLI_ADI>Teslim</GELIS_SEKLI_ADI><CINSIYET_ADI>Disi</CINSIYET_ADI><ISLEM_TARIHI>2019-12-30T10:30:58</ISLEM_TARIHI></VETNET_TABLE><VETNET_TABLE><ADI/><YAS>1</YAS><DOGUM_TARIHI xsi:type="xsd:string"/><SAGLIK_KARNESI>false</SAGLIK_KARNESI><KISIR>false</KISIR><DAVRANIS/><KUPE>false</KUPE><M_UYGULAMA_TARIHI xsi:type="xsd:string"/><TUR_ADI>Kedi</TUR_ADI><IRK_ADI>Melez</IRK_ADI><HAYVAN_MIZAC_ADI/><ANA_RENK>Tekir</ANA_RENK><TALI_RENK_1>Beyaz</TALI_RENK_1><TALI_RENK_2/><ISARETLEME_ADI>YOK</ISARETLEME_ADI><GELIS_SEKLI_ADI/><CINSIYET_ADI>Erkek</CINSIYET_ADI><ISLEM_TARIHI>2019-12-31T12:29:06</ISLEM_TARIHI></VETNET_TABLE><VETNET_TABLE><ADI/><YAS>5</YAS><DOGUM_TARIHI xsi:type="xsd:string"/><SAGLIK_KARNESI>false</SAGLIK_KARNESI><KISIR>false</KISIR><DAVRANIS/><KUPE>false</KUPE><M_UYGULAMA_TARIHI xsi:type="xsd:string"/><TUR_ADI>Köpek</TUR_ADI><IRK_ADI>Melez</IRK_ADI><HAYVAN_MIZAC_ADI/><ANA_RENK>Kahverengi</ANA_RENK><TALI_RENK_1>Sarı</TALI_RENK_1><TALI_RENK_2/><ISARETLEME_ADI>YOK</ISARETLEME_ADI><GELIS_SEKLI_ADI/><CINSIYET_ADI>Disi</CINSIYET_ADI><ISLEM_TARIHI>2020-01-03T11:25:51</ISLEM_TARIHI></VETNET_TABLE><VETNET_TABLE><ADI>FISTIK</ADI><YAS>2</YAS><DOGUM_TARIHI xsi:type="xsd:dateTime">2018-01-01T00:00:00</DOGUM_TARIHI><SAGLIK_KARNESI>false</SAGLIK_KARNESI><KISIR>true</KISIR><DAVRANIS>UYSAL</DAVRANIS><KUPE>false</KUPE><M_UYGULAMA_TARIHI xsi:type="xsd:dateTime">2019-12-23T00:00:00</M_UYGULAMA_TARIHI><TUR_ADI>Kedi</TUR_ADI><IRK_ADI>Tekir</IRK_ADI><HAYVAN_MIZAC_ADI/><ANA_RENK>Boz</ANA_RENK><TALI_RENK_1>Boz</TALI_RENK_1><TALI_RENK_2/><ISARETLEME_ADI>YOK</ISARETLEME_ADI><GELIS_SEKLI_ADI>Teslim</GELIS_SEKLI_ADI><CINSIYET_ADI>Disi</CINSIYET_ADI><ISLEM_TARIHI>2020-01-02T10:41:29</ISLEM_TARIHI></VETNET_TABLE><VETNET_TABLE><ADI/><YAS>1</YAS><DOGUM_TARIHI xsi:type="xsd:string"/><SAGLIK_KARNESI>false</SAGLIK_KARNESI><KISIR>false</KISIR><DAVRANIS/><KUPE>false</KUPE><M_UYGULAMA_TARIHI xsi:type="xsd:string"/><TUR_ADI>Köpek</TUR_ADI><IRK_ADI>Golden Retriever</IRK_ADI><HAYVAN_MIZAC_ADI/><ANA_RENK>Kahverengi</ANA_RENK><TALI_RENK_1>Kahverengi</TALI_RENK_1><TALI_RENK_2/><ISARETLEME_ADI>YOK</ISARETLEME_ADI><GELIS_SEKLI_ADI/><CINSIYET_ADI>Erkek</CINSIYET_ADI><ISLEM_TARIHI>2020-01-14T11:51:58</ISLEM_TARIHI></VETNET_TABLE><VETNET_TABLE><ADI/><YAS>1</YAS><DOGUM_TARIHI xsi:type="xsd:string"/><SAGLIK_KARNESI>false</SAGLIK_KARNESI><KISIR>false</KISIR><DAVRANIS/><KUPE>false</KUPE><M_UYGULAMA_TARIHI xsi:type="xsd:string"/><TUR_ADI>Kedi</TUR_ADI><IRK_ADI>Melez</IRK_ADI><HAYVAN_MIZAC_ADI/><ANA_RENK>Tekir</ANA_RENK><TALI_RENK_1>Tekir</TALI_RENK_1><TALI_RENK_2/><ISARETLEME_ADI>YOK</ISARETLEME_ADI><GELIS_SEKLI_ADI/><CINSIYET_ADI>Erkek</CINSIYET_ADI><ISLEM_TARIHI>2020-01-07T15:33:36</ISLEM_TARIHI></VETNET_TABLE><VETNET_TABLE><ADI/><YAS>2</YAS><DOGUM_TARIHI xsi:type="xsd:string"/><SAGLIK_KARNESI>false</SAGLIK_KARNESI><KISIR>false</KISIR><DAVRANIS/><KUPE>false</KUPE><M_UYGULAMA_TARIHI xsi:type="xsd:dateTime">2020-01-05T00:00:00</M_UYGULAMA_TARIHI><TUR_ADI>Köpek</TUR_ADI><IRK_ADI>Melez</IRK_ADI><HAYVAN_MIZAC_ADI/><ANA_RENK>Beyaz</ANA_RENK><TALI_RENK_1>Sarı</TALI_RENK_1><TALI_RENK_2/><ISARETLEME_ADI>YOK</ISARETLEME_ADI><GELIS_SEKLI_ADI/><CINSIYET_ADI>Disi</CINSIYET_ADI><ISLEM_TARIHI>2020-01-30T14:55:44</ISLEM_TARIHI></VETNET_TABLE><VETNET_TABLE><ADI/><YAS>1</YAS><DOGUM_TARIHI xsi:type="xsd:string"/><SAGLIK_KARNESI>false</SAGLIK_KARNESI><KISIR>true</KISIR><DAVRANIS/><KUPE>false</KUPE><M_UYGULAMA_TARIHI xsi:type="xsd:dateTime">2020-01-04T00:00:00</M_UYGULAMA_TARIHI><TUR_ADI>Kedi</TUR_ADI><IRK_ADI>Melez</IRK_ADI><HAYVAN_MIZAC_ADI/><ANA_RENK>Siyah</ANA_RENK><TALI_RENK_1>Kahverengi</TALI_RENK_1><TALI_RENK_2>Beyaz</TALI_RENK_2><ISARETLEME_ADI>YOK</ISARETLEME_ADI><GELIS_SEKLI_ADI/><CINSIYET_ADI>Disi</CINSIYET_ADI><ISLEM_TARIHI>2020-01-06T12:04:30</ISLEM_TARIHI></VETNET_TABLE><VETNET_TABLE><ADI>PABLO</ADI><YAS>1</YAS><DOGUM_TARIHI xsi:type="xsd:dateTime">2019-09-01T00:00:00</DOGUM_TARIHI><SAGLIK_KARNESI>false</SAGLIK_KARNESI><KISIR>false</KISIR><DAVRANIS>UYSAL</DAVRANIS><KUPE>false</KUPE><M_UYGULAMA_TARIHI xsi:type="xsd:dateTime">2020-01-03T00:00:00</M_UYGULAMA_TARIHI><TUR_ADI>Kedi</TUR_ADI><IRK_ADI>Tekir</IRK_ADI><HAYVAN_MIZAC_ADI/><ANA_RENK>Siyah</ANA_RENK><TALI_RENK_1>Beyaz</TALI_RENK_1><TALI_RENK_2/><ISARETLEME_ADI>YOK</ISARETLEME_ADI><GELIS_SEKLI_ADI>Yakalanarak</GELIS_SEKLI_ADI><CINSIYET_ADI>Erkek</CINSIYET_ADI><ISLEM_TARIHI>2020-01-07T09:23:55</ISLEM_TARIHI></VETNET_TABLE><VETNET_TABLE><ADI/><YAS>4</YAS><DOGUM_TARIHI xsi:type="xsd:string"/><SAGLIK_KARNESI>false</SAGLIK_KARNESI><KISIR>false</KISIR><DAVRANIS/><KUPE>false</KUPE><M_UYGULAMA_TARIHI xsi:type="xsd:dateTime">2020-01-07T00:00:00</M_UYGULAMA_TARIHI><TUR_ADI>Kedi</TUR_ADI><IRK_ADI>Melez</IRK_ADI><HAYVAN_MIZAC_ADI/><ANA_RENK>Gri</ANA_RENK><TALI_RENK_1>Beyaz</TALI_RENK_1><TALI_RENK_2/><ISARETLEME_ADI>YOK</ISARETLEME_ADI><GELIS_SEKLI_ADI>Yakalanarak</GELIS_SEKLI_ADI><CINSIYET_ADI>Erkek</CINSIYET_ADI><ISLEM_TARIHI>2020-01-10T10:44:54</ISLEM_TARIHI></VETNET_TABLE><VETNET_TABLE><ADI/><YAS>3</YAS><DOGUM_TARIHI xsi:type="xsd:dateTime">2017-01-01T00:00:00</DOGUM_TARIHI><SAGLIK_KARNESI>false</SAGLIK_KARNESI><KISIR>true</KISIR><DAVRANIS/><KUPE>false</KUPE><M_UYGULAMA_TARIHI xsi:type="xsd:dateTime">2020-01-07T00:00:00</M_UYGULAMA_TARIHI><TUR_ADI>Köpek</TUR_ADI><IRK_ADI>Melez</IRK_ADI><HAYVAN_MIZAC_ADI/><ANA_RENK>Beyaz</ANA_RENK><TALI_RENK_1>Beyaz</TALI_RENK_1><TALI_RENK_2/><ISARETLEME_ADI>YOK</ISARETLEME_ADI><GELIS_SEKLI_ADI>Yakalanarak</GELIS_SEKLI_ADI><CINSIYET_ADI>Erkek</CINSIYET_ADI><ISLEM_TARIHI>2020-01-08T14:13:25</ISLEM_TARIHI></VETNET_TABLE><VETNET_TABLE><ADI/><YAS>2</YAS><DOGUM_TARIHI xsi:type="xsd:dateTime">2018-01-01T00:00:00</DOGUM_TARIHI><SAGLIK_KARNESI>false</SAGLIK_KARNESI><KISIR>true</KISIR><DAVRANIS>Uysal</DAVRANIS><KUPE>false</KUPE><M_UYGULAMA_TARIHI xsi:type="xsd:dateTime">2020-01-07T00:00:00</M_UYGULAMA_TARIHI><TUR_ADI>Köpek</TUR_ADI><IRK_ADI>Melez</IRK_ADI><HAYVAN_MIZAC_ADI/><ANA_RENK>Sarı</ANA_RENK><TALI_RENK_1>Beyaz</TALI_RENK_1><TALI_RENK_2/><ISARETLEME_ADI>YOK</ISARETLEME_ADI><GELIS_SEKLI_ADI>Bayıltarak</GELIS_SEKLI_ADI><CINSIYET_ADI>Erkek</CINSIYET_ADI><ISLEM_TARIHI>2020-01-20T11:07:10</ISLEM_TARIHI></VETNET_TABLE><VETNET_TABLE><ADI/><YAS>2</YAS><DOGUM_TARIHI xsi:type="xsd:dateTime">2018-01-01T00:00:00</DOGUM_TARIHI><SAGLIK_KARNESI>false</SAGLIK_KARNESI><KISIR>true</KISIR><DAVRANIS>Uysal</DAVRANIS><KUPE>false</KUPE><M_UYGULAMA_TARIHI xsi:type="xsd:dateTime">2018-01-07T00:00:00</M_UYGULAMA_TARIHI><TUR_ADI>Köpek</TUR_ADI><IRK_ADI>Melez</IRK_ADI><HAYVAN_MIZAC_ADI/><ANA_RENK>Siyah</ANA_RENK><TALI_RENK_1>Kahverengi</TALI_RENK_1><TALI_RENK_2/><ISARETLEME_ADI>YOK</ISARETLEME_ADI><GELIS_SEKLI_ADI>Bayıltarak</GELIS_SEKLI_ADI><CINSIYET_ADI>Disi</CINSIYET_ADI><ISLEM_TARIHI>2020-01-13T15:44:47</ISLEM_TARIHI></VETNET_TABLE><VETNET_TABLE><ADI/><YAS>1</YAS><DOGUM_TARIHI xsi:type="xsd:string"/><SAGLIK_KARNESI>false</SAGLIK_KARNESI><KISIR>true</KISIR><DAVRANIS/><KUPE>false</KUPE><M_UYGULAMA_TARIHI xsi:type="xsd:dateTime">2020-01-08T00:00:00</M_UYGULAMA_TARIHI><TUR_ADI>Kedi</TUR_ADI><IRK_ADI>Melez</IRK_ADI><HAYVAN_MIZAC_ADI/><ANA_RENK>Siyah</ANA_RENK><TALI_RENK_1>Beyaz</TALI_RENK_1><TALI_RENK_2/><ISARETLEME_ADI>YOK</ISARETLEME_ADI><GELIS_SEKLI_ADI>Yakalanarak</GELIS_SEKLI_ADI><CINSIYET_ADI>Disi</CINSIYET_ADI><ISLEM_TARIHI>2020-01-27T11:41:12</ISLEM_TARIHI></VETNET_TABLE><VETNET_TABLE><ADI/><YAS>1</YAS><DOGUM_TARIHI xsi:type="xsd:string"/><SAGLIK_KARNESI>false</SAGLIK_KARNESI><KISIR>false</KISIR><DAVRANIS/><KUPE>false</KUPE><M_UYGULAMA_TARIHI xsi:type="xsd:string"/><TUR_ADI>Kedi</TUR_ADI><IRK_ADI>Melez</IRK_ADI><HAYVAN_MIZAC_ADI/><ANA_RENK>Beyaz</ANA_RENK><TALI_RENK_1>Tekir</TALI_RENK_1><TALI_RENK_2/><ISARETLEME_ADI>YOK</ISARETLEME_ADI><GELIS_SEKLI_ADI/><CINSIYET_ADI>Disi</CINSIYET_ADI><ISLEM_TARIHI>2020-01-08T13:48:44</ISLEM_TARIHI></VETNET_TABLE><VETNET_TABLE><ADI/><YAS>1</YAS><DOGUM_TARIHI xsi:type="xsd:dateTime">2019-10-01T00:00:00</DOGUM_TARIHI><SAGLIK_KARNESI>false</SAGLIK_KARNESI><KISIR>false</KISIR><DAVRANIS/><KUPE>false</KUPE><M_UYGULAMA_TARIHI xsi:type="xsd:dateTime">2020-01-08T00:00:00</M_UYGULAMA_TARIHI><TUR_ADI>Kedi</TUR_ADI><IRK_ADI>Tekir</IRK_ADI><HAYVAN_MIZAC_ADI/><ANA_RENK>Beyaz</ANA_RENK><TALI_RENK_1>Tekir</TALI_RENK_1><TALI_RENK_2/><ISARETLEME_ADI>YOK</ISARETLEME_ADI><GELIS_SEKLI_ADI>Yakalanarak</GELIS_SEKLI_ADI><CINSIYET_ADI>Disi</CINSIYET_ADI><ISLEM_TARIHI>2020-01-08T15:44:19</ISLEM_TARIHI></VETNET_TABLE><VETNET_TABLE><ADI>HERA</ADI><YAS>3</YAS><DOGUM_TARIHI xsi:type="xsd:dateTime">2017-12-01T00:00:00</DOGUM_TARIHI><SAGLIK_KARNESI>false</SAGLIK_KARNESI><KISIR>false</KISIR><DAVRANIS/><KUPE>false</KUPE><M_UYGULAMA_TARIHI xsi:type="xsd:string"/><TUR_ADI>Köpek</TUR_ADI><IRK_ADI>Melez</IRK_ADI><HAYVAN_MIZAC_ADI/><ANA_RENK>Siyah</ANA_RENK><TALI_RENK_1>Siyah</TALI_RENK_1><TALI_RENK_2/><ISARETLEME_ADI>YOK</ISARETLEME_ADI><GELIS_SEKLI_ADI>Yakalanarak</GELIS_SEKLI_ADI><CINSIYET_ADI>Disi</CINSIYET_ADI><ISLEM_TARIHI>2020-01-13T15:41:27</ISLEM_TARIHI></VETNET_TABLE><VETNET_TABLE><ADI/><YAS>1</YAS><DOGUM_TARIHI xsi:type="xsd:string"/><SAGLIK_KARNESI>false</SAGLIK_KARNESI><KISIR>false</KISIR><DAVRANIS/><KUPE>false</KUPE><M_UYGULAMA_TARIHI xsi:type="xsd:dateTime">2019-12-21T00:00:00</M_UYGULAMA_TARIHI><TUR_ADI>Köpek</TUR_ADI><IRK_ADI>Melez</IRK_ADI><HAYVAN_MIZAC_ADI/><ANA_RENK>Siyah</ANA_RENK><TALI_RENK_1>Siyah</TALI_RENK_1><TALI_RENK_2/><ISARETLEME_ADI>YOK</ISARETLEME_ADI><GELIS_SEKLI_ADI/><CINSIYET_ADI>Erkek</CINSIYET_ADI><ISLEM_TARIHI>2020-01-10T10:45:11</ISLEM_TARIHI></VETNET_TABLE><VETNET_TABLE><ADI/><YAS>3</YAS><DOGUM_TARIHI xsi:type="xsd:string"/><SAGLIK_KARNESI>false</SAGLIK_KARNESI><KISIR>true</KISIR><DAVRANIS/><KUPE>false</KUPE><M_UYGULAMA_TARIHI xsi:type="xsd:dateTime">2020-01-10T00:00:00</M_UYGULAMA_TARIHI><TUR_ADI>Kedi</TUR_ADI><IRK_ADI>Melez</IRK_ADI><HAYVAN_MIZAC_ADI/><ANA_RENK>Sarı</ANA_RENK><TALI_RENK_1>Sarı</TALI_RENK_1><TALI_RENK_2/><ISARETLEME_ADI>KULAK ÇENTİK</ISARETLEME_ADI><GELIS_SEKLI_ADI/><CINSIYET_ADI>Erkek</CINSIYET_ADI><ISLEM_TARIHI>2020-01-26T15:25:13</ISLEM_TARIHI></VETNET_TABLE><VETNET_TABLE><ADI/><YAS>1</YAS><DOGUM_TARIHI xsi:type="xsd:string"/><SAGLIK_KARNESI>false</SAGLIK_KARNESI><KISIR>false</KISIR><DAVRANIS/><KUPE>false</KUPE><M_UYGULAMA_TARIHI xsi:type="xsd:string"/><TUR_ADI>Kedi</TUR_ADI><IRK_ADI>Melez</IRK_ADI><HAYVAN_MIZAC_ADI/><ANA_RENK>Sarı</ANA_RENK><TALI_RENK_1>Beyaz</TALI_RENK_1><TALI_RENK_2/><ISARETLEME_ADI>YOK</ISARETLEME_ADI><GELIS_SEKLI_ADI/><CINSIYET_ADI>Erkek</CINSIYET_ADI><ISLEM_TARIHI>2020-01-14T11:59:06</ISLEM_TARIHI></VETNET_TABLE><VETNET_TABLE><ADI/><YAS>1</YAS><DOGUM_TARIHI xsi:type="xsd:string"/><SAGLIK_KARNESI>false</SAGLIK_KARNESI><KISIR>false</KISIR><DAVRANIS/><KUPE>false</KUPE><M_UYGULAMA_TARIHI xsi:type="xsd:string"/><TUR_ADI>Köpek</TUR_ADI><IRK_ADI>Alaskan Husky</IRK_ADI><HAYVAN_MIZAC_ADI/><ANA_RENK>Boz</ANA_RENK><TALI_RENK_1>Siyah</TALI_RENK_1><TALI_RENK_2/><ISARETLEME_ADI>YOK</ISARETLEME_ADI><GELIS_SEKLI_ADI/><CINSIYET_ADI>Disi</CINSIYET_ADI><ISLEM_TARIHI>2020-01-15T13:47:18</ISLEM_TARIHI></VETNET_TABLE><VETNET_TABLE><ADI/><YAS>3</YAS><DOGUM_TARIHI xsi:type="xsd:dateTime">2017-01-01T00:00:00</DOGUM_TARIHI><SAGLIK_KARNESI>false</SAGLIK_KARNESI><KISIR>true</KISIR><DAVRANIS>Uysal</DAVRANIS><KUPE>false</KUPE><M_UYGULAMA_TARIHI xsi:type="xsd:dateTime">2020-01-13T00:00:00</M_UYGULAMA_TARIHI><TUR_ADI>Köpek</TUR_ADI><IRK_ADI>Melez</IRK_ADI><HAYVAN_MIZAC_ADI/><ANA_RENK>Sarı</ANA_RENK><TALI_RENK_1>Sarı</TALI_RENK_1><TALI_RENK_2/><ISARETLEME_ADI>YOK</ISARETLEME_ADI><GELIS_SEKLI_ADI>Bayıltarak</GELIS_SEKLI_ADI><CINSIYET_ADI>Disi</CINSIYET_ADI><ISLEM_TARIHI>2020-01-20T11:11:29</ISLEM_TARIHI></VETNET_TABLE><VETNET_TABLE><ADI/><YAS>2</YAS><DOGUM_TARIHI xsi:type="xsd:string"/><SAGLIK_KARNESI>false</SAGLIK_KARNESI><KISIR>false</KISIR><DAVRANIS/><KUPE>false</KUPE><M_UYGULAMA_TARIHI xsi:type="xsd:string"/><TUR_ADI>Kedi</TUR_ADI><IRK_ADI>Melez</IRK_ADI><HAYVAN_MIZAC_ADI/><ANA_RENK>Tekir</ANA_RENK><TALI_RENK_1>Beyaz</TALI_RENK_1><TALI_RENK_2/><ISARETLEME_ADI>YOK</ISARETLEME_ADI><GELIS_SEKLI_ADI/><CINSIYET_ADI>Disi</CINSIYET_ADI><ISLEM_TARIHI>2020-01-14T15:03:20</ISLEM_TARIHI></VETNET_TABLE><VETNET_TABLE><ADI/><YAS>3</YAS><DOGUM_TARIHI xsi:type="xsd:string"/><SAGLIK_KARNESI>false</SAGLIK_KARNESI><KISIR>true</KISIR><DAVRANIS/><KUPE>false</KUPE><M_UYGULAMA_TARIHI xsi:type="xsd:dateTime">2020-01-15T00:00:00</M_UYGULAMA_TARIHI><TUR_ADI>Köpek</TUR_ADI><IRK_ADI>İngiliz Cocker Spaniel</IRK_ADI><HAYVAN_MIZAC_ADI/><ANA_RENK>Kahverengi</ANA_RENK><TALI_RENK_1>Beyaz</TALI_RENK_1><TALI_RENK_2/><ISARETLEME_ADI>TATOO</ISARETLEME_ADI><GELIS_SEKLI_ADI>Terk Edilme</GELIS_SEKLI_ADI><CINSIYET_ADI>Erkek</CINSIYET_ADI><ISLEM_TARIHI>2020-01-26T15:22:33</ISLEM_TARIHI></VETNET_TABLE><VETNET_TABLE><ADI/><YAS>3</YAS><DOGUM_TARIHI xsi:type="xsd:dateTime">2017-01-15T00:00:00</DOGUM_TARIHI><SAGLIK_KARNESI>false</SAGLIK_KARNESI><KISIR>true</KISIR><DAVRANIS/><KUPE>false</KUPE><M_UYGULAMA_TARIHI xsi:type="xsd:dateTime">2020-01-15T00:00:00</M_UYGULAMA_TARIHI><TUR_ADI>Köpek</TUR_ADI><IRK_ADI>Melez</IRK_ADI><HAYVAN_MIZAC_ADI/><ANA_RENK>Kahverengi</ANA_RENK><TALI_RENK_1>Kahverengi</TALI_RENK_1><TALI_RENK_2/><ISARETLEME_ADI>YOK</ISARETLEME_ADI><GELIS_SEKLI_ADI/><CINSIYET_ADI>Erkek</CINSIYET_ADI><ISLEM_TARIHI>2020-01-23T12:47:01</ISLEM_TARIHI></VETNET_TABLE><VETNET_TABLE><ADI/><YAS>4</YAS><DOGUM_TARIHI xsi:type="xsd:dateTime">2016-01-15T00:00:00</DOGUM_TARIHI><SAGLIK_KARNESI>false</SAGLIK_KARNESI><KISIR>true</KISIR><DAVRANIS/><KUPE>false</KUPE><M_UYGULAMA_TARIHI xsi:type="xsd:dateTime">2020-01-15T00:00:00</M_UYGULAMA_TARIHI><TUR_ADI>Köpek</TUR_ADI><IRK_ADI>Melez</IRK_ADI><HAYVAN_MIZAC_ADI/><ANA_RENK>Krem</ANA_RENK><TALI_RENK_1>Siyah</TALI_RENK_1><TALI_RENK_2/><ISARETLEME_ADI>YOK</ISARETLEME_ADI><GELIS_SEKLI_ADI/><CINSIYET_ADI>Erkek</CINSIYET_ADI><ISLEM_TARIHI>2020-01-23T12:45:29</ISLEM_TARIHI></VETNET_TABLE><VETNET_TABLE><ADI/><YAS>8</YAS><DOGUM_TARIHI xsi:type="xsd:string"/><SAGLIK_KARNESI>false</SAGLIK_KARNESI><KISIR>false</KISIR><DAVRANIS/><KUPE>false</KUPE><M_UYGULAMA_TARIHI xsi:type="xsd:dateTime">2020-01-15T00:00:00</M_UYGULAMA_TARIHI><TUR_ADI>Kedi</TUR_ADI><IRK_ADI>Melez</IRK_ADI><HAYVAN_MIZAC_ADI/><ANA_RENK>Beyaz</ANA_RENK><TALI_RENK_1>Sarı</TALI_RENK_1><TALI_RENK_2/><ISARETLEME_ADI>YOK</ISARETLEME_ADI><GELIS_SEKLI_ADI/><CINSIYET_ADI>Disi</CINSIYET_ADI><ISLEM_TARIHI>2020-01-20T10:19:47</ISLEM_TARIHI></VETNET_TABLE><VETNET_TABLE><ADI/><YAS>1</YAS><DOGUM_TARIHI xsi:type="xsd:string"/><SAGLIK_KARNESI>false</SAGLIK_KARNESI><KISIR>false</KISIR><DAVRANIS/><KUPE>false</KUPE><M_UYGULAMA_TARIHI xsi:type="xsd:dateTime">2020-01-17T00:00:00</M_UYGULAMA_TARIHI><TUR_ADI>Köpek</TUR_ADI><IRK_ADI>Melez</IRK_ADI><HAYVAN_MIZAC_ADI/><ANA_RENK>Beyaz</ANA_RENK><TALI_RENK_1>Gri</TALI_RENK_1><TALI_RENK_2/><ISARETLEME_ADI>YOK</ISARETLEME_ADI><GELIS_SEKLI_ADI/><CINSIYET_ADI>Disi</CINSIYET_ADI><ISLEM_TARIHI>2020-01-20T10:19:53</ISLEM_TARIHI></VETNET_TABLE><VETNET_TABLE><ADI/><YAS>3</YAS><DOGUM_TARIHI xsi:type="xsd:string"/><SAGLIK_KARNESI>false</SAGLIK_KARNESI><KISIR>false</KISIR><DAVRANIS/><KUPE>false</KUPE><M_UYGULAMA_TARIHI xsi:type="xsd:string"/><TUR_ADI>Köpek</TUR_ADI><IRK_ADI>Melez</IRK_ADI><HAYVAN_MIZAC_ADI/><ANA_RENK>Siyah</ANA_RENK><TALI_RENK_1>Beyaz</TALI_RENK_1><TALI_RENK_2/><ISARETLEME_ADI>YOK</ISARETLEME_ADI><GELIS_SEKLI_ADI/><CINSIYET_ADI>Erkek</CINSIYET_ADI><ISLEM_TARIHI>2020-01-22T10:08:36</ISLEM_TARIHI></VETNET_TABLE><VETNET_TABLE><ADI/><YAS>3</YAS><DOGUM_TARIHI xsi:type="xsd:dateTime">2017-01-01T00:00:00</DOGUM_TARIHI><SAGLIK_KARNESI>false</SAGLIK_KARNESI><KISIR>true</KISIR><DAVRANIS>Uysal</DAVRANIS><KUPE>false</KUPE><M_UYGULAMA_TARIHI xsi:type="xsd:dateTime">2020-01-22T00:00:00</M_UYGULAMA_TARIHI><TUR_ADI>Köpek</TUR_ADI><IRK_ADI>Melez</IRK_ADI><HAYVAN_MIZAC_ADI/><ANA_RENK>Sarı</ANA_RENK><TALI_RENK_1>Sarı</TALI_RENK_1><TALI_RENK_2/><ISARETLEME_ADI>YOK</ISARETLEME_ADI><GELIS_SEKLI_ADI>Bayıltarak</GELIS_SEKLI_ADI><CINSIYET_ADI>Disi</CINSIYET_ADI><ISLEM_TARIHI>2020-01-27T17:23:40</ISLEM_TARIHI></VETNET_TABLE><VETNET_TABLE><ADI/><YAS>5</YAS><DOGUM_TARIHI xsi:type="xsd:string"/><SAGLIK_KARNESI>false</SAGLIK_KARNESI><KISIR>false</KISIR><DAVRANIS/><KUPE>false</KUPE><M_UYGULAMA_TARIHI xsi:type="xsd:string"/><TUR_ADI>Köpek</TUR_ADI><IRK_ADI>Melez</IRK_ADI><HAYVAN_MIZAC_ADI/><ANA_RENK>Sarı</ANA_RENK><TALI_RENK_1>Beyaz</TALI_RENK_1><TALI_RENK_2/><ISARETLEME_ADI>YOK</ISARETLEME_ADI><GELIS_SEKLI_ADI/><CINSIYET_ADI>Disi</CINSIYET_ADI><ISLEM_TARIHI>2020-01-31T14:49:31</ISLEM_TARIHI></VETNET_TABLE></ArrayOfVETNET_TABLE>